<?xml version="1.0" encoding="UTF-8"?>
<Guild>
  <Id>219691219334217695</Id>
  <Name>Aurora Noctum</Name>
  <Level>8</Level>
  <Experience>39484</Experience>
  <MOTD>Greenscale: 8:30PM Tuesday 3rd May! Dont forget to grab the daily rift quests from the crafting area, as well as your daily experts. Rift Raids now happening minimum 1 night per week in lead up to Greenscale.</MOTD>
  <Ranks>
    <Rank>
      <Id>0</Id>
      <Name>Leader</Name>
      <CanOfficerChat>True</CanOfficerChat>
      <CanGuildChatListen>True</CanGuildChatListen>
      <CanGuildChatSpeak>True</CanGuildChatSpeak>
      <CanSetMOTD>True</CanSetMOTD>
      <CanEditOfficerNotes>True</CanEditOfficerNotes>
      <CanPromote>True</CanPromote>
      <CanDemote>True</CanDemote>
      <CanKick>True</CanKick>
      <CanEditRanks>True</CanEditRanks>
      <CanInvite>True</CanInvite>
      <CanQuestAccept>True</CanQuestAccept>
      <CanQuestAbandon>True</CanQuestAbandon>
      <CanQuestComplete>True</CanQuestComplete>
      <CanPerkTrain>True</CanPerkTrain>
      <CanRallyPointSet>True</CanRallyPointSet>
    </Rank>
    <Rank>
      <Id>1</Id>
      <Name>Not used</Name>
      <CanOfficerChat>True</CanOfficerChat>
      <CanGuildChatListen>True</CanGuildChatListen>
      <CanGuildChatSpeak>True</CanGuildChatSpeak>
      <CanSetMOTD>True</CanSetMOTD>
      <CanEditOfficerNotes>True</CanEditOfficerNotes>
      <CanPromote>True</CanPromote>
      <CanDemote>True</CanDemote>
      <CanKick>True</CanKick>
      <CanEditRanks>True</CanEditRanks>
      <CanInvite>True</CanInvite>
      <CanQuestAccept>True</CanQuestAccept>
      <CanQuestAbandon>True</CanQuestAbandon>
      <CanQuestComplete>True</CanQuestComplete>
      <CanPerkTrain>True</CanPerkTrain>
      <CanRallyPointSet>True</CanRallyPointSet>
    </Rank>
    <Rank>
      <Id>2</Id>
      <Name>Not used .</Name>
      <CanOfficerChat>False</CanOfficerChat>
      <CanGuildChatListen>False</CanGuildChatListen>
      <CanGuildChatSpeak>False</CanGuildChatSpeak>
      <CanSetMOTD>False</CanSetMOTD>
      <CanEditOfficerNotes>False</CanEditOfficerNotes>
      <CanPromote>False</CanPromote>
      <CanDemote>False</CanDemote>
      <CanKick>False</CanKick>
      <CanEditRanks>False</CanEditRanks>
      <CanInvite>False</CanInvite>
      <CanQuestAccept>False</CanQuestAccept>
      <CanQuestAbandon>False</CanQuestAbandon>
      <CanQuestComplete>False</CanQuestComplete>
      <CanPerkTrain>False</CanPerkTrain>
      <CanRallyPointSet>False</CanRallyPointSet>
    </Rank>
    <Rank>
      <Id>3</Id>
      <Name>Officer</Name>
      <CanOfficerChat>True</CanOfficerChat>
      <CanGuildChatListen>True</CanGuildChatListen>
      <CanGuildChatSpeak>True</CanGuildChatSpeak>
      <CanSetMOTD>True</CanSetMOTD>
      <CanEditOfficerNotes>True</CanEditOfficerNotes>
      <CanPromote>True</CanPromote>
      <CanDemote>True</CanDemote>
      <CanKick>True</CanKick>
      <CanEditRanks>True</CanEditRanks>
      <CanInvite>True</CanInvite>
      <CanQuestAccept>True</CanQuestAccept>
      <CanQuestAbandon>True</CanQuestAbandon>
      <CanQuestComplete>True</CanQuestComplete>
      <CanPerkTrain>True</CanPerkTrain>
      <CanRallyPointSet>True</CanRallyPointSet>
    </Rank>
    <Rank>
      <Id>4</Id>
      <Name>Officer Alt</Name>
      <CanOfficerChat>True</CanOfficerChat>
      <CanGuildChatListen>True</CanGuildChatListen>
      <CanGuildChatSpeak>True</CanGuildChatSpeak>
      <CanSetMOTD>True</CanSetMOTD>
      <CanEditOfficerNotes>True</CanEditOfficerNotes>
      <CanPromote>True</CanPromote>
      <CanDemote>True</CanDemote>
      <CanKick>True</CanKick>
      <CanEditRanks>True</CanEditRanks>
      <CanInvite>True</CanInvite>
      <CanQuestAccept>True</CanQuestAccept>
      <CanQuestAbandon>True</CanQuestAbandon>
      <CanQuestComplete>True</CanQuestComplete>
      <CanPerkTrain>True</CanPerkTrain>
      <CanRallyPointSet>True</CanRallyPointSet>
    </Rank>
    <Rank>
      <Id>5</Id>
      <Name>Senior Member</Name>
      <CanOfficerChat>False</CanOfficerChat>
      <CanGuildChatListen>True</CanGuildChatListen>
      <CanGuildChatSpeak>True</CanGuildChatSpeak>
      <CanSetMOTD>False</CanSetMOTD>
      <CanEditOfficerNotes>False</CanEditOfficerNotes>
      <CanPromote>False</CanPromote>
      <CanDemote>False</CanDemote>
      <CanKick>False</CanKick>
      <CanEditRanks>False</CanEditRanks>
      <CanInvite>False</CanInvite>
      <CanQuestAccept>True</CanQuestAccept>
      <CanQuestAbandon>False</CanQuestAbandon>
      <CanQuestComplete>True</CanQuestComplete>
      <CanPerkTrain>False</CanPerkTrain>
      <CanRallyPointSet>True</CanRallyPointSet>
    </Rank>
    <Rank>
      <Id>6</Id>
      <Name>Senior Alt</Name>
      <CanOfficerChat>False</CanOfficerChat>
      <CanGuildChatListen>True</CanGuildChatListen>
      <CanGuildChatSpeak>True</CanGuildChatSpeak>
      <CanSetMOTD>False</CanSetMOTD>
      <CanEditOfficerNotes>False</CanEditOfficerNotes>
      <CanPromote>False</CanPromote>
      <CanDemote>False</CanDemote>
      <CanKick>False</CanKick>
      <CanEditRanks>False</CanEditRanks>
      <CanInvite>False</CanInvite>
      <CanQuestAccept>True</CanQuestAccept>
      <CanQuestAbandon>False</CanQuestAbandon>
      <CanQuestComplete>True</CanQuestComplete>
      <CanPerkTrain>False</CanPerkTrain>
      <CanRallyPointSet>True</CanRallyPointSet>
    </Rank>
    <Rank>
      <Id>7</Id>
      <Name>Member</Name>
      <CanOfficerChat>False</CanOfficerChat>
      <CanGuildChatListen>True</CanGuildChatListen>
      <CanGuildChatSpeak>True</CanGuildChatSpeak>
      <CanSetMOTD>False</CanSetMOTD>
      <CanEditOfficerNotes>False</CanEditOfficerNotes>
      <CanPromote>False</CanPromote>
      <CanDemote>False</CanDemote>
      <CanKick>False</CanKick>
      <CanEditRanks>False</CanEditRanks>
      <CanInvite>False</CanInvite>
      <CanQuestAccept>False</CanQuestAccept>
      <CanQuestAbandon>False</CanQuestAbandon>
      <CanQuestComplete>True</CanQuestComplete>
      <CanPerkTrain>False</CanPerkTrain>
      <CanRallyPointSet>True</CanRallyPointSet>
    </Rank>
    <Rank>
      <Id>8</Id>
      <Name>Member Alt</Name>
      <CanOfficerChat>False</CanOfficerChat>
      <CanGuildChatListen>True</CanGuildChatListen>
      <CanGuildChatSpeak>True</CanGuildChatSpeak>
      <CanSetMOTD>False</CanSetMOTD>
      <CanEditOfficerNotes>False</CanEditOfficerNotes>
      <CanPromote>False</CanPromote>
      <CanDemote>False</CanDemote>
      <CanKick>False</CanKick>
      <CanEditRanks>False</CanEditRanks>
      <CanInvite>False</CanInvite>
      <CanQuestAccept>False</CanQuestAccept>
      <CanQuestAbandon>False</CanQuestAbandon>
      <CanQuestComplete>True</CanQuestComplete>
      <CanPerkTrain>False</CanPerkTrain>
      <CanRallyPointSet>True</CanRallyPointSet>
    </Rank>
    <Rank>
      <Id>9</Id>
      <Name>Newb</Name>
      <CanOfficerChat>False</CanOfficerChat>
      <CanGuildChatListen>True</CanGuildChatListen>
      <CanGuildChatSpeak>True</CanGuildChatSpeak>
      <CanSetMOTD>False</CanSetMOTD>
      <CanEditOfficerNotes>False</CanEditOfficerNotes>
      <CanPromote>False</CanPromote>
      <CanDemote>False</CanDemote>
      <CanKick>False</CanKick>
      <CanEditRanks>False</CanEditRanks>
      <CanInvite>False</CanInvite>
      <CanQuestAccept>False</CanQuestAccept>
      <CanQuestAbandon>False</CanQuestAbandon>
      <CanQuestComplete>True</CanQuestComplete>
      <CanPerkTrain>False</CanPerkTrain>
      <CanRallyPointSet>False</CanRallyPointSet>
    </Rank>
  </Ranks>
  <Members>
    <Member>
      <Name>Aurora</Name>
      <Rank>4</Rank>
      <Level>50</Level>
      <Calling>Cleric</Calling>
      <Joined>2011-02-25T12:43:39.557</Joined>
      <IsOnline>True</IsOnline>
      <AFK>False</AFK>
      <LastLogOutTime>2011-04-30T09:12:58.728</LastLogOutTime>
      <PersonalNotes>Mel</PersonalNotes>
      <OfficerNotes>Alt - Melodius</OfficerNotes>
      <GuildXPContribution>0</GuildXPContribution>
    </Member>
    <Member>
      <Name>Taipan</Name>
      <Rank>7</Rank>
      <Level>19</Level>
      <Calling>Mage</Calling>
      <Joined>2011-02-24T19:30:13.525</Joined>
      <IsOnline>False</IsOnline>
      <AFK>False</AFK>
      <LastLogOutTime>2011-03-31T12:04:33.732</LastLogOutTime>
      <PersonalNotes></PersonalNotes>
      <OfficerNotes>Main - Taipan</OfficerNotes>
      <GuildXPContribution>0</GuildXPContribution>
    </Member>
    <Member>
      <Name>Demyte</Name>
      <Rank>0</Rank>
      <Level>50</Level>
      <Calling>Warrior</Calling>
      <Joined>2011-02-24T19:29:03.471</Joined>
      <IsOnline>True</IsOnline>
      <AFK>False</AFK>
      <LastLogOutTime>2011-04-30T03:50:41.973</LastLogOutTime>
      <PersonalNotes>^-- I&apos;m with him</PersonalNotes>
      <OfficerNotes>Main - Demyte</OfficerNotes>
      <GuildXPContribution>0</GuildXPContribution>
    </Member>
    <Member>
      <Name>Asdran</Name>
      <Rank>5</Rank>
      <Level>49</Level>
      <Calling>Warrior</Calling>
      <Joined>2011-02-25T08:42:55.609</Joined>
      <IsOnline>False</IsOnline>
      <AFK>False</AFK>
      <LastLogOutTime>2011-04-27T11:34:25.141</LastLogOutTime>
      <PersonalNotes>Arilan (eq2)</PersonalNotes>
      <OfficerNotes>Main - Arilan</OfficerNotes>
      <GuildXPContribution>0</GuildXPContribution>
    </Member>
    <Member>
      <Name>Trixi</Name>
      <Rank>5</Rank>
      <Level>50</Level>
      <Calling>Mage</Calling>
      <Joined>2011-02-24T19:29:46.460</Joined>
      <IsOnline>False</IsOnline>
      <AFK>True</AFK>
      <LastLogOutTime>2011-04-30T01:24:54.981</LastLogOutTime>
      <PersonalNotes>Trixi Mk II</PersonalNotes>
      <OfficerNotes>Main - Trixi 2</OfficerNotes>
      <GuildXPContribution>0</GuildXPContribution>
    </Member>
    <Member>
      <Name>Melthia</Name>
      <Rank>3</Rank>
      <Level>50</Level>
      <Calling>Mage</Calling>
      <Joined>2011-04-15T10:03:35.215</Joined>
      <IsOnline>False</IsOnline>
      <AFK>False</AFK>
      <LastLogOutTime>2011-04-30T09:05:36.449</LastLogOutTime>
      <PersonalNotes>Melodius</PersonalNotes>
      <OfficerNotes>Main - Melodius</OfficerNotes>
      <GuildXPContribution>0</GuildXPContribution>
    </Member>
    <Member>
      <Name>Mamba</Name>
      <Rank>8</Rank>
      <Level>18</Level>
      <Calling>Cleric</Calling>
      <Joined>2011-03-21T08:53:36.216</Joined>
      <IsOnline>False</IsOnline>
      <AFK>False</AFK>
      <LastLogOutTime>2011-03-31T12:06:48.746</LastLogOutTime>
      <PersonalNotes>Taipans Alt</PersonalNotes>
      <OfficerNotes>Alt - Taipan/Kriat</OfficerNotes>
      <GuildXPContribution>0</GuildXPContribution>
    </Member>
    <Member>
      <Name>Kattriandra</Name>
      <Rank>7</Rank>
      <Level>50</Level>
      <Calling>Rogue</Calling>
      <Joined>2011-02-24T19:30:00.711</Joined>
      <IsOnline>False</IsOnline>
      <AFK>False</AFK>
      <LastLogOutTime>2011-04-29T02:42:18.700</LastLogOutTime>
      <PersonalNotes>Allure/Katriella/KLee</PersonalNotes>
      <OfficerNotes>Main - Kattriandra</OfficerNotes>
      <GuildXPContribution>0</GuildXPContribution>
    </Member>
    <Member>
      <Name>Jrahn</Name>
      <Rank>5</Rank>
      <Level>50</Level>
      <Calling>Rogue</Calling>
      <Joined>2011-02-24T19:42:22.628</Joined>
      <IsOnline>False</IsOnline>
      <AFK>False</AFK>
      <LastLogOutTime>2011-04-21T07:27:48.798</LastLogOutTime>
      <PersonalNotes>Xzan/Caelib</PersonalNotes>
      <OfficerNotes>Main - Xzan</OfficerNotes>
      <GuildXPContribution>0</GuildXPContribution>
    </Member>
    <Member>
      <Name>Viktoriya</Name>
      <Rank>7</Rank>
      <Level>50</Level>
      <Calling>Rogue</Calling>
      <Joined>2011-02-24T21:46:33.929</Joined>
      <IsOnline>False</IsOnline>
      <AFK>False</AFK>
      <LastLogOutTime>2011-04-30T09:43:43.882</LastLogOutTime>
      <PersonalNotes></PersonalNotes>
      <OfficerNotes>Main - Viktoriya</OfficerNotes>
      <GuildXPContribution>0</GuildXPContribution>
    </Member>
    <Member>
      <Name>Sikk</Name>
      <Rank>6</Rank>
      <Level>7</Level>
      <Calling>Warrior</Calling>
      <Joined>2011-03-01T05:02:22.420</Joined>
      <IsOnline>False</IsOnline>
      <AFK>False</AFK>
      <LastLogOutTime>2011-04-21T07:52:53.532</LastLogOutTime>
      <PersonalNotes>Sikkem/Kernos</PersonalNotes>
      <OfficerNotes>Alt - Kernos</OfficerNotes>
      <GuildXPContribution>0</GuildXPContribution>
    </Member>
    <Member>
      <Name>Ielond</Name>
      <Rank>6</Rank>
      <Level>12</Level>
      <Calling>Mage</Calling>
      <Joined>2011-03-22T11:27:19.26</Joined>
      <IsOnline>False</IsOnline>
      <AFK>False</AFK>
      <LastLogOutTime>2011-04-26T11:21:54.555</LastLogOutTime>
      <PersonalNotes></PersonalNotes>
      <OfficerNotes>Alt - Asdran (Arilan)</OfficerNotes>
      <GuildXPContribution>0</GuildXPContribution>
    </Member>
    <Member>
      <Name>Melodius</Name>
      <Rank>4</Rank>
      <Level>44</Level>
      <Calling>Rogue</Calling>
      <Joined>2011-02-25T12:41:58.362</Joined>
      <IsOnline>False</IsOnline>
      <AFK>False</AFK>
      <LastLogOutTime>2011-04-29T13:15:56.454</LastLogOutTime>
      <PersonalNotes></PersonalNotes>
      <OfficerNotes>Alt - Melodius</OfficerNotes>
      <GuildXPContribution>0</GuildXPContribution>
    </Member>
    <Member>
      <Name>Hera</Name>
      <Rank>4</Rank>
      <Level>27</Level>
      <Calling>Warrior</Calling>
      <Joined>2011-02-25T12:45:37.801</Joined>
      <IsOnline>False</IsOnline>
      <AFK>False</AFK>
      <LastLogOutTime>2011-04-22T09:44:46.116</LastLogOutTime>
      <PersonalNotes>Melodius as a Warrior</PersonalNotes>
      <OfficerNotes>Alt - Melodius</OfficerNotes>
      <GuildXPContribution>0</GuildXPContribution>
    </Member>
    <Member>
      <Name>Uluvyen</Name>
      <Rank>5</Rank>
      <Level>50</Level>
      <Calling>Rogue</Calling>
      <Joined>2011-02-24T19:31:22.728</Joined>
      <IsOnline>True</IsOnline>
      <AFK>False</AFK>
      <LastLogOutTime>2011-04-30T08:30:51.909</LastLogOutTime>
      <PersonalNotes>Cadvan</PersonalNotes>
      <OfficerNotes>Main - Cadvan</OfficerNotes>
      <GuildXPContribution>0</GuildXPContribution>
    </Member>
    <Member>
      <Name>Raptess</Name>
      <Rank>5</Rank>
      <Level>50</Level>
      <Calling>Mage</Calling>
      <Joined>2011-02-24T20:19:21.100</Joined>
      <IsOnline>False</IsOnline>
      <AFK>False</AFK>
      <LastLogOutTime>2011-04-30T05:08:58.463</LastLogOutTime>
      <PersonalNotes></PersonalNotes>
      <OfficerNotes>Main - Raptess</OfficerNotes>
      <GuildXPContribution>0</GuildXPContribution>
    </Member>
    <Member>
      <Name>Kriat</Name>
      <Rank>8</Rank>
      <Level>48</Level>
      <Calling>Warrior</Calling>
      <Joined>2011-02-26T04:06:50.706</Joined>
      <IsOnline>False</IsOnline>
      <AFK>False</AFK>
      <LastLogOutTime>2011-03-31T11:52:49.687</LastLogOutTime>
      <PersonalNotes>Taipan&apos;s alt</PersonalNotes>
      <OfficerNotes>Alt - Taipan</OfficerNotes>
      <GuildXPContribution>0</GuildXPContribution>
    </Member>
    <Member>
      <Name>Nedkelly</Name>
      <Rank>3</Rank>
      <Level>50</Level>
      <Calling>Warrior</Calling>
      <Joined>2011-02-24T20:22:29.867</Joined>
      <IsOnline>False</IsOnline>
      <AFK>False</AFK>
      <LastLogOutTime>2011-04-08T14:32:59.991</LastLogOutTime>
      <PersonalNotes></PersonalNotes>
      <OfficerNotes>Main - Nedkelly</OfficerNotes>
      <GuildXPContribution>0</GuildXPContribution>
    </Member>
    <Member>
      <Name>Ned</Name>
      <Rank>4</Rank>
      <Level>1</Level>
      <Calling>Rogue</Calling>
      <Joined>2011-02-24T20:29:17.396</Joined>
      <IsOnline>False</IsOnline>
      <AFK>False</AFK>
      <LastLogOutTime>2011-03-07T08:42:38.564</LastLogOutTime>
      <PersonalNotes></PersonalNotes>
      <OfficerNotes>Alt - Nedkelly</OfficerNotes>
      <GuildXPContribution>0</GuildXPContribution>
    </Member>
    <Member>
      <Name>Raed</Name>
      <Rank>3</Rank>
      <Level>50</Level>
      <Calling>Rogue</Calling>
      <Joined>2011-02-24T20:32:57.280</Joined>
      <IsOnline>True</IsOnline>
      <AFK>False</AFK>
      <LastLogOutTime>2011-04-30T08:02:08.640</LastLogOutTime>
      <PersonalNotes>Jark</PersonalNotes>
      <OfficerNotes>Main - Raed/Jark</OfficerNotes>
      <GuildXPContribution>0</GuildXPContribution>
    </Member>
    <Member>
      <Name>Xans</Name>
      <Rank>5</Rank>
      <Level>50</Level>
      <Calling>Rogue</Calling>
      <Joined>2011-02-24T22:36:16.797</Joined>
      <IsOnline>False</IsOnline>
      <AFK>False</AFK>
      <LastLogOutTime>2011-04-10T05:52:35.843</LastLogOutTime>
      <PersonalNotes></PersonalNotes>
      <OfficerNotes>Main - Xans</OfficerNotes>
      <GuildXPContribution>0</GuildXPContribution>
    </Member>
    <Member>
      <Name>Devoran</Name>
      <Rank>4</Rank>
      <Level>12</Level>
      <Calling>Mage</Calling>
      <Joined>2011-02-24T22:20:18.361</Joined>
      <IsOnline>False</IsOnline>
      <AFK>False</AFK>
      <LastLogOutTime>2011-04-26T11:41:56.470</LastLogOutTime>
      <PersonalNotes>Moo</PersonalNotes>
      <OfficerNotes>Alt - Devoran</OfficerNotes>
      <GuildXPContribution>0</GuildXPContribution>
    </Member>
    <Member>
      <Name>Kitsa</Name>
      <Rank>5</Rank>
      <Level>50</Level>
      <Calling>Rogue</Calling>
      <Joined>2011-02-24T22:18:33.435</Joined>
      <IsOnline>True</IsOnline>
      <AFK>False</AFK>
      <LastLogOutTime>2011-04-29T14:55:51.102</LastLogOutTime>
      <PersonalNotes>kitsa... duh (evilsar)</PersonalNotes>
      <OfficerNotes>Main - Kitsa</OfficerNotes>
      <GuildXPContribution>0</GuildXPContribution>
    </Member>
    <Member>
      <Name>Zimmy</Name>
      <Rank>5</Rank>
      <Level>32</Level>
      <Calling>Rogue</Calling>
      <Joined>2011-02-24T22:41:34.813</Joined>
      <IsOnline>False</IsOnline>
      <AFK>False</AFK>
      <LastLogOutTime>2011-04-29T07:31:10.577</LastLogOutTime>
      <PersonalNotes></PersonalNotes>
      <OfficerNotes>Main - Zim</OfficerNotes>
      <GuildXPContribution>0</GuildXPContribution>
    </Member>
    <Member>
      <Name>Tyranny</Name>
      <Rank>5</Rank>
      <Level>43</Level>
      <Calling>Cleric</Calling>
      <Joined>2011-02-24T22:42:08.618</Joined>
      <IsOnline>False</IsOnline>
      <AFK>False</AFK>
      <LastLogOutTime>2011-04-29T21:46:25.942</LastLogOutTime>
      <PersonalNotes>Amadicina</PersonalNotes>
      <OfficerNotes>Main - Tyranny</OfficerNotes>
      <GuildXPContribution>0</GuildXPContribution>
    </Member>
    <Member>
      <Name>Wrenn</Name>
      <Rank>5</Rank>
      <Level>50</Level>
      <Calling>Rogue</Calling>
      <Joined>2011-04-25T08:39:57.55</Joined>
      <IsOnline>False</IsOnline>
      <AFK>False</AFK>
      <LastLogOutTime>2011-04-29T05:52:24.413</LastLogOutTime>
      <PersonalNotes>&lt;-- Wrenn</PersonalNotes>
      <OfficerNotes>Main - Wrenn</OfficerNotes>
      <GuildXPContribution>0</GuildXPContribution>
    </Member>
    <Member>
      <Name>China</Name>
      <Rank>7</Rank>
      <Level>43</Level>
      <Calling>Rogue</Calling>
      <Joined>2011-02-24T22:23:05.546</Joined>
      <IsOnline>False</IsOnline>
      <AFK>False</AFK>
      <LastLogOutTime>2011-03-08T03:02:52.401</LastLogOutTime>
      <PersonalNotes></PersonalNotes>
      <OfficerNotes>Main - China</OfficerNotes>
      <GuildXPContribution>0</GuildXPContribution>
    </Member>
    <Member>
      <Name>Deornoth</Name>
      <Rank>3</Rank>
      <Level>50</Level>
      <Calling>Warrior</Calling>
      <Joined>2011-02-24T22:15:29.981</Joined>
      <IsOnline>True</IsOnline>
      <AFK>False</AFK>
      <LastLogOutTime>2011-04-30T07:41:14.523</LastLogOutTime>
      <PersonalNotes>I like pie</PersonalNotes>
      <OfficerNotes>Main - Devoran</OfficerNotes>
      <GuildXPContribution>0</GuildXPContribution>
    </Member>
    <Member>
      <Name>Brickwall</Name>
      <Rank>7</Rank>
      <Level>47</Level>
      <Calling>Warrior</Calling>
      <Joined>2011-02-26T07:08:16.547</Joined>
      <IsOnline>False</IsOnline>
      <AFK>False</AFK>
      <LastLogOutTime>2011-03-26T06:55:04.681</LastLogOutTime>
      <PersonalNotes></PersonalNotes>
      <OfficerNotes>Main - Brickwall</OfficerNotes>
      <GuildXPContribution>0</GuildXPContribution>
    </Member>
    <Member>
      <Name>Zekhan</Name>
      <Rank>6</Rank>
      <Level>21</Level>
      <Calling>Mage</Calling>
      <Joined>2011-02-25T06:32:33.831</Joined>
      <IsOnline>False</IsOnline>
      <AFK>False</AFK>
      <LastLogOutTime>2011-04-30T07:52:30.757</LastLogOutTime>
      <PersonalNotes></PersonalNotes>
      <OfficerNotes>Alt - Chandria</OfficerNotes>
      <GuildXPContribution>0</GuildXPContribution>
    </Member>
    <Member>
      <Name>Xochitl</Name>
      <Rank>6</Rank>
      <Level>15</Level>
      <Calling>Warrior</Calling>
      <Joined>2011-02-24T22:16:55.121</Joined>
      <IsOnline>False</IsOnline>
      <AFK>False</AFK>
      <LastLogOutTime>2011-04-29T14:57:20.515</LastLogOutTime>
      <PersonalNotes>Kitsa/Evilsar</PersonalNotes>
      <OfficerNotes>Alt - Kitsa</OfficerNotes>
      <GuildXPContribution>0</GuildXPContribution>
    </Member>
    <Member>
      <Name>Bandaid</Name>
      <Rank>8</Rank>
      <Level>18</Level>
      <Calling>Cleric</Calling>
      <Joined>2011-03-08T10:18:40.167</Joined>
      <IsOnline>False</IsOnline>
      <AFK>False</AFK>
      <LastLogOutTime>2011-03-13T01:50:09.661</LastLogOutTime>
      <PersonalNotes></PersonalNotes>
      <OfficerNotes>Alt - Brickwall</OfficerNotes>
      <GuildXPContribution>0</GuildXPContribution>
    </Member>
    <Member>
      <Name>Erliond</Name>
      <Rank>6</Rank>
      <Level>20</Level>
      <Calling>Warrior</Calling>
      <Joined>2011-02-28T23:13:39.899</Joined>
      <IsOnline>False</IsOnline>
      <AFK>False</AFK>
      <LastLogOutTime>2011-03-23T02:52:59.970</LastLogOutTime>
      <PersonalNotes>zimmy&apos;s tank alt :)</PersonalNotes>
      <OfficerNotes>Alt - Zimvex</OfficerNotes>
      <GuildXPContribution>0</GuildXPContribution>
    </Member>
    <Member>
      <Name>Amadicina</Name>
      <Rank>6</Rank>
      <Level>15</Level>
      <Calling>Mage</Calling>
      <Joined>2011-04-20T09:34:52.337</Joined>
      <IsOnline>False</IsOnline>
      <AFK>False</AFK>
      <LastLogOutTime>2011-04-28T21:12:10.529</LastLogOutTime>
      <PersonalNotes></PersonalNotes>
      <OfficerNotes>Alt - Tyranny</OfficerNotes>
      <GuildXPContribution>0</GuildXPContribution>
    </Member>
    <Member>
      <Name>Chandria</Name>
      <Rank>5</Rank>
      <Level>17</Level>
      <Calling>Cleric</Calling>
      <Joined>2011-02-25T11:30:34.755</Joined>
      <IsOnline>False</IsOnline>
      <AFK>False</AFK>
      <LastLogOutTime>2011-04-26T11:01:14.71</LastLogOutTime>
      <PersonalNotes></PersonalNotes>
      <OfficerNotes>Main - Chandy</OfficerNotes>
      <GuildXPContribution>0</GuildXPContribution>
    </Member>
    <Member>
      <Name>Megla</Name>
      <Rank>6</Rank>
      <Level>16</Level>
      <Calling>Mage</Calling>
      <Joined>2011-03-01T00:38:59.268</Joined>
      <IsOnline>False</IsOnline>
      <AFK>False</AFK>
      <LastLogOutTime>2011-03-27T08:57:00.148</LastLogOutTime>
      <PersonalNotes>zimmy&apos;s alt Mage</PersonalNotes>
      <OfficerNotes>Alt - Zim</OfficerNotes>
      <GuildXPContribution>0</GuildXPContribution>
    </Member>
    <Member>
      <Name>Bradigan</Name>
      <Rank>7</Rank>
      <Level>31</Level>
      <Calling>Mage</Calling>
      <Joined>2011-02-24T22:30:09.506</Joined>
      <IsOnline>False</IsOnline>
      <AFK>False</AFK>
      <LastLogOutTime>2011-04-10T10:38:29.977</LastLogOutTime>
      <PersonalNotes></PersonalNotes>
      <OfficerNotes>Main - Bradigan</OfficerNotes>
      <GuildXPContribution>0</GuildXPContribution>
    </Member>
    <Member>
      <Name>Keala</Name>
      <Rank>6</Rank>
      <Level>16</Level>
      <Calling>Cleric</Calling>
      <Joined>2011-03-01T09:11:32.344</Joined>
      <IsOnline>False</IsOnline>
      <AFK>False</AFK>
      <LastLogOutTime>2011-03-21T01:15:14.811</LastLogOutTime>
      <PersonalNotes>zimmy&apos;s healer alt</PersonalNotes>
      <OfficerNotes>Alt - Zimmy</OfficerNotes>
      <GuildXPContribution>0</GuildXPContribution>
    </Member>
    <Member>
      <Name>Anna</Name>
      <Rank>5</Rank>
      <Level>22</Level>
      <Calling>Cleric</Calling>
      <Joined>2011-02-25T01:37:27.265</Joined>
      <IsOnline>False</IsOnline>
      <AFK>False</AFK>
      <LastLogOutTime>2011-04-09T12:25:30.486</LastLogOutTime>
      <PersonalNotes></PersonalNotes>
      <OfficerNotes>Main - Ashlar</OfficerNotes>
      <GuildXPContribution>0</GuildXPContribution>
    </Member>
    <Member>
      <Name>Azawrath</Name>
      <Rank>3</Rank>
      <Level>50</Level>
      <Calling>Rogue</Calling>
      <Joined>2011-02-25T01:02:23.969</Joined>
      <IsOnline>True</IsOnline>
      <AFK>False</AFK>
      <LastLogOutTime>2011-04-29T13:20:13.935</LastLogOutTime>
      <PersonalNotes>Power Ranger</PersonalNotes>
      <OfficerNotes>Main - Azawrath</OfficerNotes>
      <GuildXPContribution>0</GuildXPContribution>
    </Member>
    <Member>
      <Name>Jehira</Name>
      <Rank>5</Rank>
      <Level>50</Level>
      <Calling>Cleric</Calling>
      <Joined>2011-02-25T02:36:49.448</Joined>
      <IsOnline>False</IsOnline>
      <AFK>False</AFK>
      <LastLogOutTime>2011-04-29T14:32:28.629</LastLogOutTime>
      <PersonalNotes>lol</PersonalNotes>
      <OfficerNotes>Main - Jehira</OfficerNotes>
      <GuildXPContribution>0</GuildXPContribution>
    </Member>
    <Member>
      <Name>Zamm</Name>
      <Rank>5</Rank>
      <Level>40</Level>
      <Calling>Mage</Calling>
      <Joined>2011-02-25T03:06:14.916</Joined>
      <IsOnline>False</IsOnline>
      <AFK>False</AFK>
      <LastLogOutTime>2011-04-29T11:28:06.131</LastLogOutTime>
      <PersonalNotes></PersonalNotes>
      <OfficerNotes>Main - Zam</OfficerNotes>
      <GuildXPContribution>0</GuildXPContribution>
    </Member>
    <Member>
      <Name>Korthal</Name>
      <Rank>7</Rank>
      <Level>28</Level>
      <Calling>Warrior</Calling>
      <Joined>2011-02-25T04:47:59.148</Joined>
      <IsOnline>False</IsOnline>
      <AFK>False</AFK>
      <LastLogOutTime>2011-04-16T14:27:30.592</LastLogOutTime>
      <PersonalNotes>Korthal</PersonalNotes>
      <OfficerNotes>Main - Korthal</OfficerNotes>
      <GuildXPContribution>0</GuildXPContribution>
    </Member>
    <Member>
      <Name>Maradonia</Name>
      <Rank>7</Rank>
      <Level>30</Level>
      <Calling>Warrior</Calling>
      <Joined>2011-02-25T07:39:30.501</Joined>
      <IsOnline>False</IsOnline>
      <AFK>False</AFK>
      <LastLogOutTime>2011-03-27T11:36:12.135</LastLogOutTime>
      <PersonalNotes></PersonalNotes>
      <OfficerNotes>Main - Maradonia</OfficerNotes>
      <GuildXPContribution>0</GuildXPContribution>
    </Member>
    <Member>
      <Name>Dariyn</Name>
      <Rank>3</Rank>
      <Level>50</Level>
      <Calling>Cleric</Calling>
      <Joined>2011-04-27T09:13:30.507</Joined>
      <IsOnline>True</IsOnline>
      <AFK>False</AFK>
      <LastLogOutTime>2011-04-30T09:03:06.240</LastLogOutTime>
      <PersonalNotes></PersonalNotes>
      <OfficerNotes>Main - Dariyn</OfficerNotes>
      <GuildXPContribution>0</GuildXPContribution>
    </Member>
    <Member>
      <Name>Monzara</Name>
      <Rank>5</Rank>
      <Level>43</Level>
      <Calling>Rogue</Calling>
      <Joined>2011-02-25T07:57:08.531</Joined>
      <IsOnline>False</IsOnline>
      <AFK>False</AFK>
      <LastLogOutTime>2011-04-30T06:47:03.620</LastLogOutTime>
      <PersonalNotes>Master Outfitter :)</PersonalNotes>
      <OfficerNotes>Main - Monz</OfficerNotes>
      <GuildXPContribution>0</GuildXPContribution>
    </Member>
    <Member>
      <Name>Silvercloak</Name>
      <Rank>5</Rank>
      <Level>22</Level>
      <Calling>Cleric</Calling>
      <Joined>2011-02-25T11:15:34.310</Joined>
      <IsOnline>False</IsOnline>
      <AFK>False</AFK>
      <LastLogOutTime>2011-04-30T01:17:20.135</LastLogOutTime>
      <PersonalNotes></PersonalNotes>
      <OfficerNotes>Main - Silvercloak</OfficerNotes>
      <GuildXPContribution>0</GuildXPContribution>
    </Member>
    <Member>
      <Name>Reirn</Name>
      <Rank>7</Rank>
      <Level>50</Level>
      <Calling>Mage</Calling>
      <Joined>2011-02-25T10:24:27.625</Joined>
      <IsOnline>False</IsOnline>
      <AFK>False</AFK>
      <LastLogOutTime>2011-03-31T03:18:57.946</LastLogOutTime>
      <PersonalNotes></PersonalNotes>
      <OfficerNotes>Main - Reirn</OfficerNotes>
      <GuildXPContribution>0</GuildXPContribution>
    </Member>
    <Member>
      <Name>Kyopi</Name>
      <Rank>5</Rank>
      <Level>50</Level>
      <Calling>Rogue</Calling>
      <Joined>2011-02-25T08:31:46.731</Joined>
      <IsOnline>True</IsOnline>
      <AFK>False</AFK>
      <LastLogOutTime>2011-04-30T10:37:02.374</LastLogOutTime>
      <PersonalNotes>Cootric</PersonalNotes>
      <OfficerNotes>Main - Cootric</OfficerNotes>
      <GuildXPContribution>0</GuildXPContribution>
    </Member>
    <Member>
      <Name>Kyopa</Name>
      <Rank>6</Rank>
      <Level>21</Level>
      <Calling>Cleric</Calling>
      <Joined>2011-02-25T08:36:21.885</Joined>
      <IsOnline>False</IsOnline>
      <AFK>False</AFK>
      <LastLogOutTime>2011-03-04T11:33:12.243</LastLogOutTime>
      <PersonalNotes>Cootric</PersonalNotes>
      <OfficerNotes>Alt - Kyopi</OfficerNotes>
      <GuildXPContribution>0</GuildXPContribution>
    </Member>
    <Member>
      <Name>Cootric</Name>
      <Rank>6</Rank>
      <Level>1</Level>
      <Calling>Mage</Calling>
      <Joined>2011-02-25T08:40:28.780</Joined>
      <IsOnline>False</IsOnline>
      <AFK>False</AFK>
      <LastLogOutTime>2011-02-25T08:40:58.250</LastLogOutTime>
      <PersonalNotes></PersonalNotes>
      <OfficerNotes>Alt - Kyopi
</OfficerNotes>
      <GuildXPContribution>0</GuildXPContribution>
    </Member>
    <Member>
      <Name>Kaeili</Name>
      <Rank>4</Rank>
      <Level>1</Level>
      <Calling>Rogue</Calling>
      <Joined>2011-02-25T08:54:47.299</Joined>
      <IsOnline>False</IsOnline>
      <AFK>False</AFK>
      <LastLogOutTime>2011-04-09T15:04:13.305</LastLogOutTime>
      <PersonalNotes></PersonalNotes>
      <OfficerNotes>Alt - Devoran</OfficerNotes>
      <GuildXPContribution>0</GuildXPContribution>
    </Member>
    <Member>
      <Name>Kaine</Name>
      <Rank>6</Rank>
      <Level>50</Level>
      <Calling>Rogue</Calling>
      <Joined>2011-02-25T09:01:30.410</Joined>
      <IsOnline>False</IsOnline>
      <AFK>False</AFK>
      <LastLogOutTime>2011-04-30T07:52:02.301</LastLogOutTime>
      <PersonalNotes>Zipity</PersonalNotes>
      <OfficerNotes>Alt - Zip</OfficerNotes>
      <GuildXPContribution>0</GuildXPContribution>
    </Member>
    <Member>
      <Name>Pixi</Name>
      <Rank>5</Rank>
      <Level>50</Level>
      <Calling>Warrior</Calling>
      <Joined>2011-02-25T09:07:33.783</Joined>
      <IsOnline>False</IsOnline>
      <AFK>False</AFK>
      <LastLogOutTime>2011-04-30T05:23:29.372</LastLogOutTime>
      <PersonalNotes>I&apos;ll tank for you!!!</PersonalNotes>
      <OfficerNotes>Main - Trixi 1</OfficerNotes>
      <GuildXPContribution>0</GuildXPContribution>
    </Member>
    <Member>
      <Name>Deetee</Name>
      <Rank>5</Rank>
      <Level>47</Level>
      <Calling>Cleric</Calling>
      <Joined>2011-02-25T09:09:07.371</Joined>
      <IsOnline>True</IsOnline>
      <AFK>False</AFK>
      <LastLogOutTime>2011-04-29T12:21:16.284</LastLogOutTime>
      <PersonalNotes></PersonalNotes>
      <OfficerNotes>Main - DT</OfficerNotes>
      <GuildXPContribution>0</GuildXPContribution>
    </Member>
    <Member>
      <Name>Mordikaar</Name>
      <Rank>7</Rank>
      <Level>25</Level>
      <Calling>Rogue</Calling>
      <Joined>2011-02-26T00:32:13.284</Joined>
      <IsOnline>False</IsOnline>
      <AFK>False</AFK>
      <LastLogOutTime>2011-03-11T11:04:12.494</LastLogOutTime>
      <PersonalNotes></PersonalNotes>
      <OfficerNotes>Main - Mordikaar</OfficerNotes>
      <GuildXPContribution>0</GuildXPContribution>
    </Member>
    <Member>
      <Name>Avra</Name>
      <Rank>7</Rank>
      <Level>26</Level>
      <Calling>Cleric</Calling>
      <Joined>2011-02-26T00:32:34.496</Joined>
      <IsOnline>False</IsOnline>
      <AFK>False</AFK>
      <LastLogOutTime>2011-03-11T03:36:39.349</LastLogOutTime>
      <PersonalNotes></PersonalNotes>
      <OfficerNotes>Main - Avra</OfficerNotes>
      <GuildXPContribution>0</GuildXPContribution>
    </Member>
    <Member>
      <Name>Shiktyl</Name>
      <Rank>7</Rank>
      <Level>35</Level>
      <Calling>Mage</Calling>
      <Joined>2011-02-25T09:44:12.390</Joined>
      <IsOnline>False</IsOnline>
      <AFK>False</AFK>
      <LastLogOutTime>2011-04-26T11:32:05.282</LastLogOutTime>
      <PersonalNotes></PersonalNotes>
      <OfficerNotes>Main - Shiktyl</OfficerNotes>
      <GuildXPContribution>0</GuildXPContribution>
    </Member>
    <Member>
      <Name>Tarukai</Name>
      <Rank>7</Rank>
      <Level>33</Level>
      <Calling>Mage</Calling>
      <Joined>2011-02-25T09:42:22.425</Joined>
      <IsOnline>False</IsOnline>
      <AFK>False</AFK>
      <LastLogOutTime>2011-04-07T10:48:13.873</LastLogOutTime>
      <PersonalNotes>I love scotch. Scotchy, scotch, scotch. Here it goes down, down into my belly... </PersonalNotes>
      <OfficerNotes>Main - Tarukai</OfficerNotes>
      <GuildXPContribution>0</GuildXPContribution>
    </Member>
    <Member>
      <Name>Phyre</Name>
      <Rank>7</Rank>
      <Level>24</Level>
      <Calling>Mage</Calling>
      <Joined>2011-02-25T12:31:48.301</Joined>
      <IsOnline>False</IsOnline>
      <AFK>False</AFK>
      <LastLogOutTime>2011-03-17T12:29:05.880</LastLogOutTime>
      <PersonalNotes></PersonalNotes>
      <OfficerNotes>Main - Phyre</OfficerNotes>
      <GuildXPContribution>0</GuildXPContribution>
    </Member>
    <Member>
      <Name>Shadian</Name>
      <Rank>7</Rank>
      <Level>36</Level>
      <Calling>Cleric</Calling>
      <Joined>2011-02-25T09:44:56.384</Joined>
      <IsOnline>False</IsOnline>
      <AFK>False</AFK>
      <LastLogOutTime>2011-04-30T07:41:48.634</LastLogOutTime>
      <PersonalNotes>LOLPENIS</PersonalNotes>
      <OfficerNotes>Main - Shadian</OfficerNotes>
      <GuildXPContribution>0</GuildXPContribution>
    </Member>
    <Member>
      <Name>Roskam</Name>
      <Rank>5</Rank>
      <Level>50</Level>
      <Calling>Warrior</Calling>
      <Joined>2011-02-25T11:18:13.766</Joined>
      <IsOnline>False</IsOnline>
      <AFK>False</AFK>
      <LastLogOutTime>2011-04-27T13:07:14.219</LastLogOutTime>
      <PersonalNotes>Main: Armoursmith. I will make u anything if u provide mats. :)</PersonalNotes>
      <OfficerNotes>Main - Roskam</OfficerNotes>
      <GuildXPContribution>0</GuildXPContribution>
    </Member>
    <Member>
      <Name>Helbrecht</Name>
      <Rank>7</Rank>
      <Level>50</Level>
      <Calling>Cleric</Calling>
      <Joined>2011-02-25T11:05:12.843</Joined>
      <IsOnline>False</IsOnline>
      <AFK>False</AFK>
      <LastLogOutTime>2011-03-30T08:07:40.232</LastLogOutTime>
      <PersonalNotes>Winning!</PersonalNotes>
      <OfficerNotes>Main - Halbrecht</OfficerNotes>
      <GuildXPContribution>0</GuildXPContribution>
    </Member>
    <Member>
      <Name>Rastan</Name>
      <Rank>5</Rank>
      <Level>50</Level>
      <Calling>Warrior</Calling>
      <Joined>2011-02-26T11:52:59.993</Joined>
      <IsOnline>True</IsOnline>
      <AFK>False</AFK>
      <LastLogOutTime>2011-04-30T06:06:50.859</LastLogOutTime>
      <PersonalNotes>Rasta</PersonalNotes>
      <OfficerNotes>Main - Rastan</OfficerNotes>
      <GuildXPContribution>0</GuildXPContribution>
    </Member>
    <Member>
      <Name>Zeherah</Name>
      <Rank>5</Rank>
      <Level>50</Level>
      <Calling>Cleric</Calling>
      <Joined>2011-03-11T11:15:00.461</Joined>
      <IsOnline>True</IsOnline>
      <AFK>False</AFK>
      <LastLogOutTime>2011-04-29T12:55:07.246</LastLogOutTime>
      <PersonalNotes></PersonalNotes>
      <OfficerNotes>Main - Zeherah</OfficerNotes>
      <GuildXPContribution>0</GuildXPContribution>
    </Member>
    <Member>
      <Name>Roberta</Name>
      <Rank>7</Rank>
      <Level>26</Level>
      <Calling>Rogue</Calling>
      <Joined>2011-03-02T10:37:02.306</Joined>
      <IsOnline>False</IsOnline>
      <AFK>False</AFK>
      <LastLogOutTime>2011-04-30T06:01:51.702</LastLogOutTime>
      <PersonalNotes></PersonalNotes>
      <OfficerNotes>Main - Roberta</OfficerNotes>
      <GuildXPContribution>0</GuildXPContribution>
    </Member>
    <Member>
      <Name>Lluolinn</Name>
      <Rank>7</Rank>
      <Level>50</Level>
      <Calling>Warrior</Calling>
      <Joined>2011-03-11T11:15:51.700</Joined>
      <IsOnline>True</IsOnline>
      <AFK>False</AFK>
      <LastLogOutTime>2011-04-29T12:39:46.825</LastLogOutTime>
      <PersonalNotes></PersonalNotes>
      <OfficerNotes>Main - Lluolinn</OfficerNotes>
      <GuildXPContribution>0</GuildXPContribution>
    </Member>
    <Member>
      <Name>Kaleida</Name>
      <Rank>5</Rank>
      <Level>50</Level>
      <Calling>Cleric</Calling>
      <Joined>2011-02-25T11:06:23.481</Joined>
      <IsOnline>False</IsOnline>
      <AFK>False</AFK>
      <LastLogOutTime>2011-04-30T10:26:47.808</LastLogOutTime>
      <PersonalNotes>I&apos;m a PvP server! (Kallak)</PersonalNotes>
      <OfficerNotes>Main - Kallak</OfficerNotes>
      <GuildXPContribution>0</GuildXPContribution>
    </Member>
    <Member>
      <Name>Snav</Name>
      <Rank>6</Rank>
      <Level>27</Level>
      <Calling>Rogue</Calling>
      <Joined>2011-02-26T11:17:28.210</Joined>
      <IsOnline>False</IsOnline>
      <AFK>False</AFK>
      <LastLogOutTime>2011-04-04T13:47:57.565</LastLogOutTime>
      <PersonalNotes>Nills, Anila etc</PersonalNotes>
      <OfficerNotes>Alt - Nills
</OfficerNotes>
      <GuildXPContribution>0</GuildXPContribution>
    </Member>
    <Member>
      <Name>Jaenelle</Name>
      <Rank>9</Rank>
      <Level>18</Level>
      <Calling>Mage</Calling>
      <Joined>2011-04-24T09:01:36.355</Joined>
      <IsOnline>False</IsOnline>
      <AFK>False</AFK>
      <LastLogOutTime>2011-04-30T09:52:38.128</LastLogOutTime>
      <PersonalNotes></PersonalNotes>
      <OfficerNotes>Alt - Zeherah</OfficerNotes>
      <GuildXPContribution>0</GuildXPContribution>
    </Member>
    <Member>
      <Name>Nills</Name>
      <Rank>5</Rank>
      <Level>13</Level>
      <Calling>Warrior</Calling>
      <Joined>2011-02-25T11:09:32.911</Joined>
      <IsOnline>False</IsOnline>
      <AFK>False</AFK>
      <LastLogOutTime>2011-04-19T11:39:23.625</LastLogOutTime>
      <PersonalNotes></PersonalNotes>
      <OfficerNotes>Main - Nills</OfficerNotes>
      <GuildXPContribution>0</GuildXPContribution>
    </Member>
    <Member>
      <Name>Atrax</Name>
      <Rank>7</Rank>
      <Level>47</Level>
      <Calling>Warrior</Calling>
      <Joined>2011-03-01T11:37:38.878</Joined>
      <IsOnline>False</IsOnline>
      <AFK>False</AFK>
      <LastLogOutTime>2011-04-29T23:26:02.133</LastLogOutTime>
      <PersonalNotes></PersonalNotes>
      <OfficerNotes>Main - Atrax</OfficerNotes>
      <GuildXPContribution>0</GuildXPContribution>
    </Member>
    <Member>
      <Name>Lufy</Name>
      <Rank>5</Rank>
      <Level>28</Level>
      <Calling>Cleric</Calling>
      <Joined>2011-02-26T11:28:29.908</Joined>
      <IsOnline>False</IsOnline>
      <AFK>False</AFK>
      <LastLogOutTime>2011-04-30T09:07:58.833</LastLogOutTime>
      <PersonalNotes>Ryokosama</PersonalNotes>
      <OfficerNotes>Main - Ryokosama</OfficerNotes>
      <GuildXPContribution>0</GuildXPContribution>
    </Member>
    <Member>
      <Name>Ryokosama</Name>
      <Rank>6</Rank>
      <Level>23</Level>
      <Calling>Mage</Calling>
      <Joined>2011-03-08T08:48:02.238</Joined>
      <IsOnline>False</IsOnline>
      <AFK>False</AFK>
      <LastLogOutTime>2011-04-29T12:12:57.503</LastLogOutTime>
      <PersonalNotes></PersonalNotes>
      <OfficerNotes>Alt - Lufy</OfficerNotes>
      <GuildXPContribution>0</GuildXPContribution>
    </Member>
    <Member>
      <Name>Apt</Name>
      <Rank>7</Rank>
      <Level>31</Level>
      <Calling>Rogue</Calling>
      <Joined>2011-02-25T12:42:54.417</Joined>
      <IsOnline>False</IsOnline>
      <AFK>False</AFK>
      <LastLogOutTime>2011-03-19T01:37:51.273</LastLogOutTime>
      <PersonalNotes></PersonalNotes>
      <OfficerNotes>Main - Apt</OfficerNotes>
      <GuildXPContribution>0</GuildXPContribution>
    </Member>
    <Member>
      <Name>Pendreic</Name>
      <Rank>5</Rank>
      <Level>47</Level>
      <Calling>Mage</Calling>
      <Joined>2011-02-26T08:10:57.329</Joined>
      <IsOnline>True</IsOnline>
      <AFK>True</AFK>
      <LastLogOutTime>2011-04-30T07:00:23.857</LastLogOutTime>
      <PersonalNotes></PersonalNotes>
      <OfficerNotes>Main - Pend</OfficerNotes>
      <GuildXPContribution>0</GuildXPContribution>
    </Member>
    <Member>
      <Name>Azash</Name>
      <Rank>4</Rank>
      <Level>17</Level>
      <Calling>Cleric</Calling>
      <Joined>2011-04-24T03:39:23.849</Joined>
      <IsOnline>False</IsOnline>
      <AFK>False</AFK>
      <LastLogOutTime>2011-04-24T07:57:02.252</LastLogOutTime>
      <PersonalNotes></PersonalNotes>
      <OfficerNotes>Alt - Azawrath</OfficerNotes>
      <GuildXPContribution>0</GuildXPContribution>
    </Member>
    <Member>
      <Name>Tray</Name>
      <Rank>5</Rank>
      <Level>20</Level>
      <Calling>Warrior</Calling>
      <Joined>2011-02-27T09:37:13.759</Joined>
      <IsOnline>False</IsOnline>
      <AFK>False</AFK>
      <LastLogOutTime>2011-03-27T07:12:34.682</LastLogOutTime>
      <PersonalNotes></PersonalNotes>
      <OfficerNotes>Main - Skurn</OfficerNotes>
      <GuildXPContribution>0</GuildXPContribution>
    </Member>
    <Member>
      <Name>Athak</Name>
      <Rank>7</Rank>
      <Level>50</Level>
      <Calling>Rogue</Calling>
      <Joined>2011-02-26T04:48:23.350</Joined>
      <IsOnline>False</IsOnline>
      <AFK>False</AFK>
      <LastLogOutTime>2011-04-30T07:49:15.118</LastLogOutTime>
      <PersonalNotes></PersonalNotes>
      <OfficerNotes>Main - Athak</OfficerNotes>
      <GuildXPContribution>0</GuildXPContribution>
    </Member>
    <Member>
      <Name>Crimzondevil</Name>
      <Rank>7</Rank>
      <Level>30</Level>
      <Calling>Warrior</Calling>
      <Joined>2011-03-01T02:54:14.932</Joined>
      <IsOnline>False</IsOnline>
      <AFK>False</AFK>
      <LastLogOutTime>2011-03-04T10:02:48.372</LastLogOutTime>
      <PersonalNotes></PersonalNotes>
      <OfficerNotes>Main - Crimzondevil</OfficerNotes>
      <GuildXPContribution>0</GuildXPContribution>
    </Member>
    <Member>
      <Name>Cabalistic</Name>
      <Rank>5</Rank>
      <Level>24</Level>
      <Calling>Warrior</Calling>
      <Joined>2011-02-25T13:04:24.309</Joined>
      <IsOnline>False</IsOnline>
      <AFK>False</AFK>
      <LastLogOutTime>2011-04-16T07:27:24.797</LastLogOutTime>
      <PersonalNotes></PersonalNotes>
      <OfficerNotes>Main - Beszerx</OfficerNotes>
      <GuildXPContribution>0</GuildXPContribution>
    </Member>
    <Member>
      <Name>Darciphe</Name>
      <Rank>6</Rank>
      <Level>24</Level>
      <Calling>Mage</Calling>
      <Joined>2011-02-27T05:32:36.728</Joined>
      <IsOnline>False</IsOnline>
      <AFK>False</AFK>
      <LastLogOutTime>2011-04-20T18:09:33.872</LastLogOutTime>
      <PersonalNotes>Kal - Alt</PersonalNotes>
      <OfficerNotes>Alt - Kallak</OfficerNotes>
      <GuildXPContribution>0</GuildXPContribution>
    </Member>
    <Member>
      <Name>Wulstaf</Name>
      <Rank>5</Rank>
      <Level>16</Level>
      <Calling>Rogue</Calling>
      <Joined>2011-02-28T13:30:39.222</Joined>
      <IsOnline>False</IsOnline>
      <AFK>False</AFK>
      <LastLogOutTime>2011-04-04T11:07:09.151</LastLogOutTime>
      <PersonalNotes></PersonalNotes>
      <OfficerNotes>Main - Wulstaff</OfficerNotes>
      <GuildXPContribution>0</GuildXPContribution>
    </Member>
    <Member>
      <Name>Fistandtilus</Name>
      <Rank>6</Rank>
      <Level>21</Level>
      <Calling>Mage</Calling>
      <Joined>2011-03-05T14:24:59.426</Joined>
      <IsOnline>False</IsOnline>
      <AFK>False</AFK>
      <LastLogOutTime>2011-04-30T07:01:04.250</LastLogOutTime>
      <PersonalNotes></PersonalNotes>
      <OfficerNotes>Alt - Wulstaf</OfficerNotes>
      <GuildXPContribution>0</GuildXPContribution>
    </Member>
    <Member>
      <Name>Kaede</Name>
      <Rank>7</Rank>
      <Level>22</Level>
      <Calling>Rogue</Calling>
      <Joined>2011-03-03T14:13:57.462</Joined>
      <IsOnline>False</IsOnline>
      <AFK>False</AFK>
      <LastLogOutTime>2011-04-13T03:30:38.154</LastLogOutTime>
      <PersonalNotes>Sampalok</PersonalNotes>
      <OfficerNotes>Main - Sampalok</OfficerNotes>
      <GuildXPContribution>0</GuildXPContribution>
    </Member>
    <Member>
      <Name>Kernos</Name>
      <Rank>5</Rank>
      <Level>50</Level>
      <Calling>Rogue</Calling>
      <Joined>2011-02-25T20:08:44.649</Joined>
      <IsOnline>True</IsOnline>
      <AFK>False</AFK>
      <LastLogOutTime>2011-04-30T04:55:20.680</LastLogOutTime>
      <PersonalNotes>Sikkem</PersonalNotes>
      <OfficerNotes>Main - Sikkem</OfficerNotes>
      <GuildXPContribution>0</GuildXPContribution>
    </Member>
    <Member>
      <Name>Zarthaza</Name>
      <Rank>7</Rank>
      <Level>50</Level>
      <Calling>Rogue</Calling>
      <Joined>2011-02-27T00:42:09.936</Joined>
      <IsOnline>False</IsOnline>
      <AFK>False</AFK>
      <LastLogOutTime>2011-04-30T09:49:41.570</LastLogOutTime>
      <PersonalNotes></PersonalNotes>
      <OfficerNotes>Main - Zarthaza</OfficerNotes>
      <GuildXPContribution>0</GuildXPContribution>
    </Member>
    <Member>
      <Name>Spikey</Name>
      <Rank>6</Rank>
      <Level>50</Level>
      <Calling>Rogue</Calling>
      <Joined>2011-02-27T12:12:58.139</Joined>
      <IsOnline>False</IsOnline>
      <AFK>False</AFK>
      <LastLogOutTime>2011-03-31T08:11:14.915</LastLogOutTime>
      <PersonalNotes>Beserzx (cabalistic)</PersonalNotes>
      <OfficerNotes>Alt - Cabalistic</OfficerNotes>
      <GuildXPContribution>0</GuildXPContribution>
    </Member>
    <Member>
      <Name>Dangerzone</Name>
      <Rank>7</Rank>
      <Level>5</Level>
      <Calling>Warrior</Calling>
      <Joined>2011-04-15T09:58:31.59</Joined>
      <IsOnline>False</IsOnline>
      <AFK>False</AFK>
      <LastLogOutTime>2011-04-15T11:37:00.562</LastLogOutTime>
      <PersonalNotes></PersonalNotes>
      <OfficerNotes>Alt - Can&apos;t remember who</OfficerNotes>
      <GuildXPContribution>0</GuildXPContribution>
    </Member>
    <Member>
      <Name>Maljinn</Name>
      <Rank>8</Rank>
      <Level>16</Level>
      <Calling>Rogue</Calling>
      <Joined>2011-03-19T09:28:33.973</Joined>
      <IsOnline>False</IsOnline>
      <AFK>False</AFK>
      <LastLogOutTime>2011-03-20T12:31:48.266</LastLogOutTime>
      <PersonalNotes>Shad (awesome)</PersonalNotes>
      <OfficerNotes>Alt - Shadian</OfficerNotes>
      <GuildXPContribution>0</GuildXPContribution>
    </Member>
    <Member>
      <Name>Arthia</Name>
      <Rank>8</Rank>
      <Level>29</Level>
      <Calling>Rogue</Calling>
      <Joined>2011-03-19T09:30:11.723</Joined>
      <IsOnline>False</IsOnline>
      <AFK>False</AFK>
      <LastLogOutTime>2011-04-30T07:37:27.904</LastLogOutTime>
      <PersonalNotes>Tarukai</PersonalNotes>
      <OfficerNotes>Alt - Tarukai</OfficerNotes>
      <GuildXPContribution>0</GuildXPContribution>
    </Member>
    <Member>
      <Name>Dorica</Name>
      <Rank>6</Rank>
      <Level>16</Level>
      <Calling>Warrior</Calling>
      <Joined>2011-03-04T01:41:36.944</Joined>
      <IsOnline>False</IsOnline>
      <AFK>False</AFK>
      <LastLogOutTime>2011-04-25T11:35:55.327</LastLogOutTime>
      <PersonalNotes></PersonalNotes>
      <OfficerNotes>Alt - Raptess</OfficerNotes>
      <GuildXPContribution>0</GuildXPContribution>
    </Member>
    <Member>
      <Name>Sakiko</Name>
      <Rank>7</Rank>
      <Level>46</Level>
      <Calling>Mage</Calling>
      <Joined>2011-03-19T06:15:15.363</Joined>
      <IsOnline>False</IsOnline>
      <AFK>True</AFK>
      <LastLogOutTime>2011-04-30T03:18:30.512</LastLogOutTime>
      <PersonalNotes>Denrnoth&apos;s mate</PersonalNotes>
      <OfficerNotes>Main - Sakiko (frnd of Dev)</OfficerNotes>
      <GuildXPContribution>0</GuildXPContribution>
    </Member>
    <Member>
      <Name>Jylena</Name>
      <Rank>6</Rank>
      <Level>14</Level>
      <Calling>Warrior</Calling>
      <Joined>2011-03-03T12:56:09.906</Joined>
      <IsOnline>False</IsOnline>
      <AFK>False</AFK>
      <LastLogOutTime>2011-04-21T04:10:12.224</LastLogOutTime>
      <PersonalNotes></PersonalNotes>
      <OfficerNotes>Alt - Chandria</OfficerNotes>
      <GuildXPContribution>0</GuildXPContribution>
    </Member>
    <Member>
      <Name>Tricksie</Name>
      <Rank>6</Rank>
      <Level>1</Level>
      <Calling>Mage</Calling>
      <Joined>2011-02-26T09:19:19.439</Joined>
      <IsOnline>False</IsOnline>
      <AFK>False</AFK>
      <LastLogOutTime>2011-03-19T10:52:08.748</LastLogOutTime>
      <PersonalNotes></PersonalNotes>
      <OfficerNotes>Alt - Jehira</OfficerNotes>
      <GuildXPContribution>0</GuildXPContribution>
    </Member>
    <Member>
      <Name>Sykoa</Name>
      <Rank>5</Rank>
      <Level>50</Level>
      <Calling>Mage</Calling>
      <Joined>2011-02-28T13:07:05.793</Joined>
      <IsOnline>False</IsOnline>
      <AFK>False</AFK>
      <LastLogOutTime>2011-04-14T03:59:28.758</LastLogOutTime>
      <PersonalNotes></PersonalNotes>
      <OfficerNotes>Main - Doven</OfficerNotes>
      <GuildXPContribution>0</GuildXPContribution>
    </Member>
    <Member>
      <Name>Drahn</Name>
      <Rank>6</Rank>
      <Level>50</Level>
      <Calling>Cleric</Calling>
      <Joined>2011-03-01T11:27:41.267</Joined>
      <IsOnline>False</IsOnline>
      <AFK>False</AFK>
      <LastLogOutTime>2011-04-29T12:51:49.280</LastLogOutTime>
      <PersonalNotes>Xzan</PersonalNotes>
      <OfficerNotes>Main - Xzan</OfficerNotes>
      <GuildXPContribution>0</GuildXPContribution>
    </Member>
    <Member>
      <Name>Caelib</Name>
      <Rank>6</Rank>
      <Level>26</Level>
      <Calling>Mage</Calling>
      <Joined>2011-02-26T12:23:28.579</Joined>
      <IsOnline>False</IsOnline>
      <AFK>False</AFK>
      <LastLogOutTime>2011-04-26T07:44:09.856</LastLogOutTime>
      <PersonalNotes>Xzan</PersonalNotes>
      <OfficerNotes>Alt - Xzan</OfficerNotes>
      <GuildXPContribution>0</GuildXPContribution>
    </Member>
    <Member>
      <Name>Ogast</Name>
      <Rank>7</Rank>
      <Level>16</Level>
      <Calling>Cleric</Calling>
      <Joined>2011-03-04T11:38:59.768</Joined>
      <IsOnline>False</IsOnline>
      <AFK>False</AFK>
      <LastLogOutTime>2011-04-03T12:05:33.238</LastLogOutTime>
      <PersonalNotes></PersonalNotes>
      <OfficerNotes>Main - Ogast</OfficerNotes>
      <GuildXPContribution>0</GuildXPContribution>
    </Member>
    <Member>
      <Name>Beckista</Name>
      <Rank>6</Rank>
      <Level>10</Level>
      <Calling>Rogue</Calling>
      <Joined>2011-03-03T09:36:13.595</Joined>
      <IsOnline>False</IsOnline>
      <AFK>False</AFK>
      <LastLogOutTime>2011-03-09T11:55:46.950</LastLogOutTime>
      <PersonalNotes></PersonalNotes>
      <OfficerNotes>Alt - Roskam</OfficerNotes>
      <GuildXPContribution>0</GuildXPContribution>
    </Member>
    <Member>
      <Name>Zipity</Name>
      <Rank>5</Rank>
      <Level>50</Level>
      <Calling>Mage</Calling>
      <Joined>2011-02-26T18:04:49.756</Joined>
      <IsOnline>True</IsOnline>
      <AFK>False</AFK>
      <LastLogOutTime>2011-04-30T04:35:35.38</LastLogOutTime>
      <PersonalNotes></PersonalNotes>
      <OfficerNotes>Main - Zip</OfficerNotes>
      <GuildXPContribution>0</GuildXPContribution>
    </Member>
    <Member>
      <Name>Navi</Name>
      <Rank>6</Rank>
      <Level>50</Level>
      <Calling>Rogue</Calling>
      <Joined>2011-02-27T06:39:57.106</Joined>
      <IsOnline>True</IsOnline>
      <AFK>False</AFK>
      <LastLogOutTime>2011-04-30T05:13:47.499</LastLogOutTime>
      <PersonalNotes>ryokosama alt</PersonalNotes>
      <OfficerNotes>Alt - Lufy</OfficerNotes>
      <GuildXPContribution>0</GuildXPContribution>
    </Member>
    <Member>
      <Name>Ariah</Name>
      <Rank>6</Rank>
      <Level>50</Level>
      <Calling>Mage</Calling>
      <Joined>2011-02-27T02:55:22.888</Joined>
      <IsOnline>False</IsOnline>
      <AFK>False</AFK>
      <LastLogOutTime>2011-04-28T17:42:33.986</LastLogOutTime>
      <PersonalNotes>Beserzx, spikey/varnae</PersonalNotes>
      <OfficerNotes>Alt - Cabalistic</OfficerNotes>
      <GuildXPContribution>0</GuildXPContribution>
    </Member>
    <Member>
      <Name>Burlz</Name>
      <Rank>7</Rank>
      <Level>25</Level>
      <Calling>Rogue</Calling>
      <Joined>2011-02-27T04:35:56.332</Joined>
      <IsOnline>False</IsOnline>
      <AFK>False</AFK>
      <LastLogOutTime>2011-04-24T01:17:30.202</LastLogOutTime>
      <PersonalNotes></PersonalNotes>
      <OfficerNotes>Main - Burlz</OfficerNotes>
      <GuildXPContribution>0</GuildXPContribution>
    </Member>
    <Member>
      <Name>Barrakah</Name>
      <Rank>6</Rank>
      <Level>20</Level>
      <Calling>Warrior</Calling>
      <Joined>2011-02-27T07:29:22.00</Joined>
      <IsOnline>False</IsOnline>
      <AFK>False</AFK>
      <LastLogOutTime>2011-04-30T06:20:21.743</LastLogOutTime>
      <PersonalNotes>monz</PersonalNotes>
      <OfficerNotes>Alt - Dama</OfficerNotes>
      <GuildXPContribution>0</GuildXPContribution>
    </Member>
    <Member>
      <Name>Samma</Name>
      <Rank>5</Rank>
      <Level>50</Level>
      <Calling>Cleric</Calling>
      <Joined>2011-03-29T10:22:16.806</Joined>
      <IsOnline>False</IsOnline>
      <AFK>False</AFK>
      <LastLogOutTime>2011-04-30T06:31:03.499</LastLogOutTime>
      <PersonalNotes></PersonalNotes>
      <OfficerNotes>Main - Samma</OfficerNotes>
      <GuildXPContribution>0</GuildXPContribution>
    </Member>
    <Member>
      <Name>Flashpoint</Name>
      <Rank>7</Rank>
      <Level>24</Level>
      <Calling>Rogue</Calling>
      <Joined>2011-03-02T12:19:39.109</Joined>
      <IsOnline>False</IsOnline>
      <AFK>False</AFK>
      <LastLogOutTime>2011-04-10T08:10:49.240</LastLogOutTime>
      <PersonalNotes></PersonalNotes>
      <OfficerNotes>Main - Flashpoint</OfficerNotes>
      <GuildXPContribution>0</GuildXPContribution>
    </Member>
    <Member>
      <Name>Psion</Name>
      <Rank>5</Rank>
      <Level>50</Level>
      <Calling>Cleric</Calling>
      <Joined>2011-02-28T01:40:42.509</Joined>
      <IsOnline>False</IsOnline>
      <AFK>False</AFK>
      <LastLogOutTime>2011-04-30T10:44:55.759</LastLogOutTime>
      <PersonalNotes></PersonalNotes>
      <OfficerNotes>Main - Quue</OfficerNotes>
      <GuildXPContribution>0</GuildXPContribution>
    </Member>
    <Member>
      <Name>Tarsq</Name>
      <Rank>7</Rank>
      <Level>46</Level>
      <Calling>Rogue</Calling>
      <Joined>2011-03-02T01:01:58.502</Joined>
      <IsOnline>False</IsOnline>
      <AFK>False</AFK>
      <LastLogOutTime>2011-04-25T05:48:46.316</LastLogOutTime>
      <PersonalNotes></PersonalNotes>
      <OfficerNotes>Main - Tarsq</OfficerNotes>
      <GuildXPContribution>0</GuildXPContribution>
    </Member>
    <Member>
      <Name>Jrahl</Name>
      <Rank>6</Rank>
      <Level>9</Level>
      <Calling>Warrior</Calling>
      <Joined>2011-02-28T05:35:15.285</Joined>
      <IsOnline>False</IsOnline>
      <AFK>False</AFK>
      <LastLogOutTime>2011-04-20T22:43:51.291</LastLogOutTime>
      <PersonalNotes>Xzan</PersonalNotes>
      <OfficerNotes>Alt - Xzan</OfficerNotes>
      <GuildXPContribution>0</GuildXPContribution>
    </Member>
    <Member>
      <Name>Pixibank</Name>
      <Rank>6</Rank>
      <Level>1</Level>
      <Calling>Cleric</Calling>
      <Joined>2011-02-28T12:42:00.156</Joined>
      <IsOnline>False</IsOnline>
      <AFK>False</AFK>
      <LastLogOutTime>2011-02-28T12:44:03.843</LastLogOutTime>
      <PersonalNotes></PersonalNotes>
      <OfficerNotes>Alt - Pixi</OfficerNotes>
      <GuildXPContribution>0</GuildXPContribution>
    </Member>
    <Member>
      <Name>Yasmela</Name>
      <Rank>6</Rank>
      <Level>12</Level>
      <Calling>Cleric</Calling>
      <Joined>2011-03-01T06:05:13.573</Joined>
      <IsOnline>False</IsOnline>
      <AFK>False</AFK>
      <LastLogOutTime>2011-03-15T08:40:36.537</LastLogOutTime>
      <PersonalNotes>Gorefist Alt</PersonalNotes>
      <OfficerNotes>Alt - Gorefist</OfficerNotes>
      <GuildXPContribution>0</GuildXPContribution>
    </Member>
    <Member>
      <Name>Hammerstein</Name>
      <Rank>5</Rank>
      <Level>13</Level>
      <Calling>Warrior</Calling>
      <Joined>2011-03-01T07:09:47.576</Joined>
      <IsOnline>False</IsOnline>
      <AFK>False</AFK>
      <LastLogOutTime>2011-03-22T00:57:17.758</LastLogOutTime>
      <PersonalNotes>Gorefist Main</PersonalNotes>
      <OfficerNotes>Main - Gorey</OfficerNotes>
      <GuildXPContribution>0</GuildXPContribution>
    </Member>
    <Member>
      <Name>Bunyip</Name>
      <Rank>6</Rank>
      <Level>32</Level>
      <Calling>Cleric</Calling>
      <Joined>2011-03-01T07:09:49.691</Joined>
      <IsOnline>False</IsOnline>
      <AFK>False</AFK>
      <LastLogOutTime>2011-04-29T22:40:08.312</LastLogOutTime>
      <PersonalNotes>Zipity</PersonalNotes>
      <OfficerNotes>Alt - Zipity</OfficerNotes>
      <GuildXPContribution>0</GuildXPContribution>
    </Member>
    <Member>
      <Name>Nevinir</Name>
      <Rank>7</Rank>
      <Level>12</Level>
      <Calling>Mage</Calling>
      <Joined>2011-03-01T10:39:31.620</Joined>
      <IsOnline>False</IsOnline>
      <AFK>False</AFK>
      <LastLogOutTime>2011-03-02T11:50:49.810</LastLogOutTime>
      <PersonalNotes></PersonalNotes>
      <OfficerNotes>Main - Nevinir</OfficerNotes>
      <GuildXPContribution>0</GuildXPContribution>
    </Member>
    <Member>
      <Name>Rahzar</Name>
      <Rank>7</Rank>
      <Level>50</Level>
      <Calling>Warrior</Calling>
      <Joined>2011-03-07T09:59:12.396</Joined>
      <IsOnline>False</IsOnline>
      <AFK>False</AFK>
      <LastLogOutTime>2011-04-09T02:32:34.602</LastLogOutTime>
      <PersonalNotes></PersonalNotes>
      <OfficerNotes>Main - Rahzar</OfficerNotes>
      <GuildXPContribution>0</GuildXPContribution>
    </Member>
    <Member>
      <Name>Detharen</Name>
      <Rank>6</Rank>
      <Level>14</Level>
      <Calling>Rogue</Calling>
      <Joined>2011-03-03T11:56:56.450</Joined>
      <IsOnline>False</IsOnline>
      <AFK>False</AFK>
      <LastLogOutTime>2011-04-21T08:30:15.132</LastLogOutTime>
      <PersonalNotes></PersonalNotes>
      <OfficerNotes>Alt - Chandria</OfficerNotes>
      <GuildXPContribution>0</GuildXPContribution>
    </Member>
    <Member>
      <Name>Xerenat</Name>
      <Rank>6</Rank>
      <Level>16</Level>
      <Calling>Mage</Calling>
      <Joined>2011-03-02T08:19:14.765</Joined>
      <IsOnline>False</IsOnline>
      <AFK>False</AFK>
      <LastLogOutTime>2011-03-19T22:57:22.607</LastLogOutTime>
      <PersonalNotes>zimmy&apos;s other mage alt</PersonalNotes>
      <OfficerNotes>Alt - Zim</OfficerNotes>
      <GuildXPContribution>0</GuildXPContribution>
    </Member>
    <Member>
      <Name>Trigona</Name>
      <Rank>5</Rank>
      <Level>36</Level>
      <Calling>Mage</Calling>
      <Joined>2011-03-03T00:45:21.756</Joined>
      <IsOnline>False</IsOnline>
      <AFK>False</AFK>
      <LastLogOutTime>2011-04-30T06:01:03.273</LastLogOutTime>
      <PersonalNotes></PersonalNotes>
      <OfficerNotes>Main - Trigona</OfficerNotes>
      <GuildXPContribution>0</GuildXPContribution>
    </Member>
    <Member>
      <Name>Clarion</Name>
      <Rank>6</Rank>
      <Level>8</Level>
      <Calling>Rogue</Calling>
      <Joined>2011-03-02T07:40:35.377</Joined>
      <IsOnline>False</IsOnline>
      <AFK>False</AFK>
      <LastLogOutTime>2011-04-30T07:12:21.555</LastLogOutTime>
      <PersonalNotes></PersonalNotes>
      <OfficerNotes>???</OfficerNotes>
      <GuildXPContribution>0</GuildXPContribution>
    </Member>
    <Member>
      <Name>Gitara</Name>
      <Rank>6</Rank>
      <Level>12</Level>
      <Calling>Rogue</Calling>
      <Joined>2011-03-02T11:20:44.289</Joined>
      <IsOnline>False</IsOnline>
      <AFK>False</AFK>
      <LastLogOutTime>2011-03-12T11:16:36.337</LastLogOutTime>
      <PersonalNotes></PersonalNotes>
      <OfficerNotes>Alt - Gorefist</OfficerNotes>
      <GuildXPContribution>0</GuildXPContribution>
    </Member>
    <Member>
      <Name>Bolivar</Name>
      <Rank>6</Rank>
      <Level>12</Level>
      <Calling>Mage</Calling>
      <Joined>2011-03-02T08:29:27.643</Joined>
      <IsOnline>False</IsOnline>
      <AFK>False</AFK>
      <LastLogOutTime>2011-03-15T07:28:46.520</LastLogOutTime>
      <PersonalNotes>Gorefist Alt</PersonalNotes>
      <OfficerNotes>Alt - Gorefist</OfficerNotes>
      <GuildXPContribution>0</GuildXPContribution>
    </Member>
    <Member>
      <Name>Jimoin</Name>
      <Rank>5</Rank>
      <Level>35</Level>
      <Calling>Warrior</Calling>
      <Joined>2011-03-02T11:00:00.193</Joined>
      <IsOnline>False</IsOnline>
      <AFK>False</AFK>
      <LastLogOutTime>2011-04-24T13:04:17.856</LastLogOutTime>
      <PersonalNotes></PersonalNotes>
      <OfficerNotes>Main - Jimoin</OfficerNotes>
      <GuildXPContribution>0</GuildXPContribution>
    </Member>
    <Member>
      <Name>Basser</Name>
      <Rank>5</Rank>
      <Level>30</Level>
      <Calling>Cleric</Calling>
      <Joined>2011-03-02T11:21:59.993</Joined>
      <IsOnline>False</IsOnline>
      <AFK>False</AFK>
      <LastLogOutTime>2011-04-19T13:17:28.460</LastLogOutTime>
      <PersonalNotes></PersonalNotes>
      <OfficerNotes>Main - Shadoo/Basser</OfficerNotes>
      <GuildXPContribution>0</GuildXPContribution>
    </Member>
    <Member>
      <Name>Zuragon</Name>
      <Rank>6</Rank>
      <Level>10</Level>
      <Calling>Mage</Calling>
      <Joined>2011-04-24T12:25:20.457</Joined>
      <IsOnline>False</IsOnline>
      <AFK>False</AFK>
      <LastLogOutTime>2011-04-24T12:41:19.663</LastLogOutTime>
      <PersonalNotes></PersonalNotes>
      <OfficerNotes>Alt - Jimoin</OfficerNotes>
      <GuildXPContribution>0</GuildXPContribution>
    </Member>
    <Member>
      <Name>Kurro</Name>
      <Rank>7</Rank>
      <Level>50</Level>
      <Calling>Warrior</Calling>
      <Joined>2011-03-03T07:29:48.115</Joined>
      <IsOnline>False</IsOnline>
      <AFK>False</AFK>
      <LastLogOutTime>2011-04-02T02:54:18.147</LastLogOutTime>
      <PersonalNotes></PersonalNotes>
      <OfficerNotes>Main - Kurro</OfficerNotes>
      <GuildXPContribution>0</GuildXPContribution>
    </Member>
    <Member>
      <Name>Lisani</Name>
      <Rank>5</Rank>
      <Level>50</Level>
      <Calling>Mage</Calling>
      <Joined>2011-03-03T00:00:14.214</Joined>
      <IsOnline>False</IsOnline>
      <AFK>False</AFK>
      <LastLogOutTime>2011-04-30T10:48:31.323</LastLogOutTime>
      <PersonalNotes></PersonalNotes>
      <OfficerNotes>Main - Lisani</OfficerNotes>
      <GuildXPContribution>0</GuildXPContribution>
    </Member>
    <Member>
      <Name>Jaenell</Name>
      <Rank>8</Rank>
      <Level>42</Level>
      <Calling>Cleric</Calling>
      <Joined>2011-03-22T07:58:40.728</Joined>
      <IsOnline>False</IsOnline>
      <AFK>False</AFK>
      <LastLogOutTime>2011-04-24T12:04:31.551</LastLogOutTime>
      <PersonalNotes></PersonalNotes>
      <OfficerNotes>Main - Jaenell</OfficerNotes>
      <GuildXPContribution>0</GuildXPContribution>
    </Member>
    <Member>
      <Name>Asmodius</Name>
      <Rank>7</Rank>
      <Level>50</Level>
      <Calling>Mage</Calling>
      <Joined>2011-03-12T08:37:24.685</Joined>
      <IsOnline>False</IsOnline>
      <AFK>False</AFK>
      <LastLogOutTime>2011-03-30T07:50:27.719</LastLogOutTime>
      <PersonalNotes>Linkith from eq2</PersonalNotes>
      <OfficerNotes>Main - Asmodius</OfficerNotes>
      <GuildXPContribution>0</GuildXPContribution>
    </Member>
    <Member>
      <Name>Sownya</Name>
      <Rank>6</Rank>
      <Level>18</Level>
      <Calling>Cleric</Calling>
      <Joined>2011-03-04T01:43:23.219</Joined>
      <IsOnline>False</IsOnline>
      <AFK>False</AFK>
      <LastLogOutTime>2011-04-25T12:17:09.61</LastLogOutTime>
      <PersonalNotes>Raptess</PersonalNotes>
      <OfficerNotes>Alt - Raptess</OfficerNotes>
      <GuildXPContribution>0</GuildXPContribution>
    </Member>
    <Member>
      <Name>Aihryn</Name>
      <Rank>6</Rank>
      <Level>18</Level>
      <Calling>Rogue</Calling>
      <Joined>2011-03-04T01:44:45.198</Joined>
      <IsOnline>False</IsOnline>
      <AFK>False</AFK>
      <LastLogOutTime>2011-04-25T11:39:08.915</LastLogOutTime>
      <PersonalNotes>Raptess</PersonalNotes>
      <OfficerNotes>Alt - Raptess</OfficerNotes>
      <GuildXPContribution>0</GuildXPContribution>
    </Member>
    <Member>
      <Name>Hanhasil</Name>
      <Rank>6</Rank>
      <Level>16</Level>
      <Calling>Warrior</Calling>
      <Joined>2011-03-06T21:39:06.266</Joined>
      <IsOnline>False</IsOnline>
      <AFK>False</AFK>
      <LastLogOutTime>2011-03-20T08:05:25.427</LastLogOutTime>
      <PersonalNotes></PersonalNotes>
      <OfficerNotes>Alt - Zim</OfficerNotes>
      <GuildXPContribution>0</GuildXPContribution>
    </Member>
    <Member>
      <Name>Aweful</Name>
      <Rank>5</Rank>
      <Level>23</Level>
      <Calling>Mage</Calling>
      <Joined>2011-03-05T11:43:57.189</Joined>
      <IsOnline>False</IsOnline>
      <AFK>False</AFK>
      <LastLogOutTime>2011-03-31T08:24:32.230</LastLogOutTime>
      <PersonalNotes></PersonalNotes>
      <OfficerNotes>Main - Aerth</OfficerNotes>
      <GuildXPContribution>0</GuildXPContribution>
    </Member>
    <Member>
      <Name>Aland</Name>
      <Rank>5</Rank>
      <Level>42</Level>
      <Calling>Cleric</Calling>
      <Joined>2011-03-06T03:30:46.978</Joined>
      <IsOnline>False</IsOnline>
      <AFK>False</AFK>
      <LastLogOutTime>2011-04-28T08:56:19.170</LastLogOutTime>
      <PersonalNotes>It is I &quot;Elayne&quot;!! and stuff</PersonalNotes>
      <OfficerNotes>Main - Aland/Elayne</OfficerNotes>
      <GuildXPContribution>0</GuildXPContribution>
    </Member>
    <Member>
      <Name>Gale</Name>
      <Rank>6</Rank>
      <Level>41</Level>
      <Calling>Cleric</Calling>
      <Joined>2011-03-08T10:54:59.572</Joined>
      <IsOnline>False</IsOnline>
      <AFK>False</AFK>
      <LastLogOutTime>2011-04-10T06:45:09.976</LastLogOutTime>
      <PersonalNotes></PersonalNotes>
      <OfficerNotes>Alt - Ashlar</OfficerNotes>
      <GuildXPContribution>0</GuildXPContribution>
    </Member>
    <Member>
      <Name>Ellyanar</Name>
      <Rank>7</Rank>
      <Level>21</Level>
      <Calling>Rogue</Calling>
      <Joined>2011-03-20T08:07:32.830</Joined>
      <IsOnline>False</IsOnline>
      <AFK>False</AFK>
      <LastLogOutTime>2011-04-20T23:56:12.716</LastLogOutTime>
      <PersonalNotes></PersonalNotes>
      <OfficerNotes>Alt - Jaenell</OfficerNotes>
      <GuildXPContribution>0</GuildXPContribution>
    </Member>
    <Member>
      <Name>Bennura</Name>
      <Rank>5</Rank>
      <Level>50</Level>
      <Calling>Cleric</Calling>
      <Joined>2011-03-07T05:41:11.477</Joined>
      <IsOnline>False</IsOnline>
      <AFK>False</AFK>
      <LastLogOutTime>2011-04-27T09:00:15.592</LastLogOutTime>
      <PersonalNotes>is awesome</PersonalNotes>
      <OfficerNotes>Main - Abysuss</OfficerNotes>
      <GuildXPContribution>0</GuildXPContribution>
    </Member>
    <Member>
      <Name>Cadvan</Name>
      <Rank>6</Rank>
      <Level>13</Level>
      <Calling>Mage</Calling>
      <Joined>2011-03-07T09:32:14.266</Joined>
      <IsOnline>False</IsOnline>
      <AFK>False</AFK>
      <LastLogOutTime>2011-03-27T07:41:43.122</LastLogOutTime>
      <PersonalNotes></PersonalNotes>
      <OfficerNotes>Alt - Cadvan</OfficerNotes>
      <GuildXPContribution>0</GuildXPContribution>
    </Member>
    <Member>
      <Name>Athellion</Name>
      <Rank>6</Rank>
      <Level>14</Level>
      <Calling>Warrior</Calling>
      <Joined>2011-03-08T11:27:54.957</Joined>
      <IsOnline>False</IsOnline>
      <AFK>False</AFK>
      <LastLogOutTime>2011-03-12T07:42:41.440</LastLogOutTime>
      <PersonalNotes></PersonalNotes>
      <OfficerNotes>Main - Torvak</OfficerNotes>
      <GuildXPContribution>0</GuildXPContribution>
    </Member>
    <Member>
      <Name>Sari</Name>
      <Rank>5</Rank>
      <Level>50</Level>
      <Calling>Cleric</Calling>
      <Joined>2011-04-19T12:21:31.411</Joined>
      <IsOnline>False</IsOnline>
      <AFK>False</AFK>
      <LastLogOutTime>2011-04-30T07:00:42.743</LastLogOutTime>
      <PersonalNotes></PersonalNotes>
      <OfficerNotes>Main - Sariyn</OfficerNotes>
      <GuildXPContribution>0</GuildXPContribution>
    </Member>
    <Member>
      <Name>Monzaro</Name>
      <Rank>5</Rank>
      <Level>25</Level>
      <Calling>Cleric</Calling>
      <Joined>2011-03-13T05:04:25.401</Joined>
      <IsOnline>True</IsOnline>
      <AFK>False</AFK>
      <LastLogOutTime>2011-04-30T08:33:43.855</LastLogOutTime>
      <PersonalNotes></PersonalNotes>
      <OfficerNotes>Main - Monzaro</OfficerNotes>
      <GuildXPContribution>0</GuildXPContribution>
    </Member>
    <Member>
      <Name>Baku</Name>
      <Rank>7</Rank>
      <Level>23</Level>
      <Calling>Cleric</Calling>
      <Joined>2011-03-27T05:33:48.620</Joined>
      <IsOnline>False</IsOnline>
      <AFK>False</AFK>
      <LastLogOutTime>2011-03-27T11:09:44.41</LastLogOutTime>
      <PersonalNotes></PersonalNotes>
      <OfficerNotes>Main - Baku/Ruger (AN Wow)</OfficerNotes>
      <GuildXPContribution>0</GuildXPContribution>
    </Member>
    <Member>
      <Name>Raenar</Name>
      <Rank>6</Rank>
      <Level>12</Level>
      <Calling>Cleric</Calling>
      <Joined>2011-03-11T12:55:15.04</Joined>
      <IsOnline>False</IsOnline>
      <AFK>False</AFK>
      <LastLogOutTime>2011-04-22T01:41:47.895</LastLogOutTime>
      <PersonalNotes>Jimoin</PersonalNotes>
      <OfficerNotes>Alt - Jimoin</OfficerNotes>
      <GuildXPContribution>0</GuildXPContribution>
    </Member>
    <Member>
      <Name>Wattsyaugur</Name>
      <Rank>7</Rank>
      <Level>44</Level>
      <Calling>Rogue</Calling>
      <Joined>2011-04-29T09:33:32.566</Joined>
      <IsOnline>False</IsOnline>
      <AFK>False</AFK>
      <LastLogOutTime>2011-04-30T00:08:50.227</LastLogOutTime>
      <PersonalNotes></PersonalNotes>
      <OfficerNotes>Main - Wattsy (frnd of jippo)</OfficerNotes>
      <GuildXPContribution>0</GuildXPContribution>
    </Member>
    <Member>
      <Name>Caeclia</Name>
      <Rank>7</Rank>
      <Level>16</Level>
      <Calling>Warrior</Calling>
      <Joined>2011-03-16T11:10:42.622</Joined>
      <IsOnline>False</IsOnline>
      <AFK>False</AFK>
      <LastLogOutTime>2011-04-21T06:10:25.558</LastLogOutTime>
      <PersonalNotes></PersonalNotes>
      <OfficerNotes>Main - Wulstaf</OfficerNotes>
      <GuildXPContribution>0</GuildXPContribution>
    </Member>
    <Member>
      <Name>Paythan</Name>
      <Rank>5</Rank>
      <Level>35</Level>
      <Calling>Rogue</Calling>
      <Joined>2011-03-11T12:03:09.675</Joined>
      <IsOnline>False</IsOnline>
      <AFK>False</AFK>
      <LastLogOutTime>2011-04-29T11:56:55.489</LastLogOutTime>
      <PersonalNotes></PersonalNotes>
      <OfficerNotes>Main - Paythan</OfficerNotes>
      <GuildXPContribution>0</GuildXPContribution>
    </Member>
    <Member>
      <Name>Daemoni</Name>
      <Rank>7</Rank>
      <Level>44</Level>
      <Calling>Mage</Calling>
      <Joined>2011-04-29T09:45:42.611</Joined>
      <IsOnline>False</IsOnline>
      <AFK>False</AFK>
      <LastLogOutTime>2011-04-29T11:55:07.946</LastLogOutTime>
      <PersonalNotes></PersonalNotes>
      <OfficerNotes>Main - Daemoni</OfficerNotes>
      <GuildXPContribution>0</GuildXPContribution>
    </Member>
    <Member>
      <Name>Torvak</Name>
      <Rank>5</Rank>
      <Level>23</Level>
      <Calling>Warrior</Calling>
      <Joined>2011-03-14T01:45:36.922</Joined>
      <IsOnline>False</IsOnline>
      <AFK>False</AFK>
      <LastLogOutTime>2011-04-06T11:22:39.796</LastLogOutTime>
      <PersonalNotes></PersonalNotes>
      <OfficerNotes>Alt - Torvak</OfficerNotes>
      <GuildXPContribution>0</GuildXPContribution>
    </Member>
    <Member>
      <Name>Arganot</Name>
      <Rank>6</Rank>
      <Level>50</Level>
      <Calling>Mage</Calling>
      <Joined>2011-03-12T15:07:41.182</Joined>
      <IsOnline>False</IsOnline>
      <AFK>False</AFK>
      <LastLogOutTime>2011-04-24T01:55:10.951</LastLogOutTime>
      <PersonalNotes>&lt;-- Wrenn</PersonalNotes>
      <OfficerNotes>Alt - Wrenn</OfficerNotes>
      <GuildXPContribution>0</GuildXPContribution>
    </Member>
    <Member>
      <Name>Keato</Name>
      <Rank>5</Rank>
      <Level>40</Level>
      <Calling>Cleric</Calling>
      <Joined>2011-03-13T07:59:25.481</Joined>
      <IsOnline>False</IsOnline>
      <AFK>False</AFK>
      <LastLogOutTime>2011-04-30T06:34:37.178</LastLogOutTime>
      <PersonalNotes></PersonalNotes>
      <OfficerNotes>Main - Keato</OfficerNotes>
      <GuildXPContribution>0</GuildXPContribution>
    </Member>
    <Member>
      <Name>Obes</Name>
      <Rank>7</Rank>
      <Level>38</Level>
      <Calling>Warrior</Calling>
      <Joined>2011-03-13T08:08:23.973</Joined>
      <IsOnline>False</IsOnline>
      <AFK>False</AFK>
      <LastLogOutTime>2011-04-30T06:12:32.668</LastLogOutTime>
      <PersonalNotes></PersonalNotes>
      <OfficerNotes>Main - Obes (Keato frnd)</OfficerNotes>
      <GuildXPContribution>0</GuildXPContribution>
    </Member>
    <Member>
      <Name>Arasaki</Name>
      <Rank>7</Rank>
      <Level>40</Level>
      <Calling>Rogue</Calling>
      <Joined>2011-03-13T08:09:36.966</Joined>
      <IsOnline>True</IsOnline>
      <AFK>False</AFK>
      <LastLogOutTime>2011-04-30T06:34:20.742</LastLogOutTime>
      <PersonalNotes></PersonalNotes>
      <OfficerNotes>Main - Arasaki (Keato frnd)</OfficerNotes>
      <GuildXPContribution>0</GuildXPContribution>
    </Member>
    <Member>
      <Name>Havissard</Name>
      <Rank>8</Rank>
      <Level>12</Level>
      <Calling>Mage</Calling>
      <Joined>2011-03-14T05:35:33.99</Joined>
      <IsOnline>False</IsOnline>
      <AFK>False</AFK>
      <LastLogOutTime>2011-03-15T04:43:08.814</LastLogOutTime>
      <PersonalNotes></PersonalNotes>
      <OfficerNotes>Alt - Apt</OfficerNotes>
      <GuildXPContribution>0</GuildXPContribution>
    </Member>
    <Member>
      <Name>Switzerland</Name>
      <Rank>8</Rank>
      <Level>18</Level>
      <Calling>Cleric</Calling>
      <Joined>2011-03-14T08:35:28.667</Joined>
      <IsOnline>False</IsOnline>
      <AFK>False</AFK>
      <LastLogOutTime>2011-03-19T15:06:47.229</LastLogOutTime>
      <PersonalNotes></PersonalNotes>
      <OfficerNotes>Alt - Apt</OfficerNotes>
      <GuildXPContribution>0</GuildXPContribution>
    </Member>
    <Member>
      <Name>Rarrgh</Name>
      <Rank>6</Rank>
      <Level>50</Level>
      <Calling>Cleric</Calling>
      <Joined>2011-03-15T07:41:23.312</Joined>
      <IsOnline>False</IsOnline>
      <AFK>False</AFK>
      <LastLogOutTime>2011-04-30T09:48:26.632</LastLogOutTime>
      <PersonalNotes></PersonalNotes>
      <OfficerNotes>Alt - Xans</OfficerNotes>
      <GuildXPContribution>0</GuildXPContribution>
    </Member>
    <Member>
      <Name>Varnae</Name>
      <Rank>8</Rank>
      <Level>50</Level>
      <Calling>Cleric</Calling>
      <Joined>2011-03-15T13:03:04.892</Joined>
      <IsOnline>False</IsOnline>
      <AFK>False</AFK>
      <LastLogOutTime>2011-04-30T10:04:22.990</LastLogOutTime>
      <PersonalNotes>Spikey&apos;s (Beserzx)</PersonalNotes>
      <OfficerNotes>Alt - Beserx</OfficerNotes>
      <GuildXPContribution>0</GuildXPContribution>
    </Member>
    <Member>
      <Name>Burley</Name>
      <Rank>8</Rank>
      <Level>37</Level>
      <Calling>Warrior</Calling>
      <Joined>2011-03-24T11:42:04.478</Joined>
      <IsOnline>True</IsOnline>
      <AFK>False</AFK>
      <LastLogOutTime>2011-04-30T04:44:16.597</LastLogOutTime>
      <PersonalNotes></PersonalNotes>
      <OfficerNotes>Alt - Burlz</OfficerNotes>
      <GuildXPContribution>0</GuildXPContribution>
    </Member>
    <Member>
      <Name>Pixter</Name>
      <Rank>6</Rank>
      <Level>16</Level>
      <Calling>Rogue</Calling>
      <Joined>2011-03-19T09:22:24.221</Joined>
      <IsOnline>False</IsOnline>
      <AFK>False</AFK>
      <LastLogOutTime>2011-04-26T05:11:47.345</LastLogOutTime>
      <PersonalNotes>Trixi mkII</PersonalNotes>
      <OfficerNotes>Alt - Trixi Mk II</OfficerNotes>
      <GuildXPContribution>0</GuildXPContribution>
    </Member>
    <Member>
      <Name>Jrak</Name>
      <Rank>4</Rank>
      <Level>10</Level>
      <Calling>Warrior</Calling>
      <Joined>2011-03-20T06:22:53.681</Joined>
      <IsOnline>False</IsOnline>
      <AFK>False</AFK>
      <LastLogOutTime>2011-04-21T03:55:26.529</LastLogOutTime>
      <PersonalNotes></PersonalNotes>
      <OfficerNotes>Alt - Jark</OfficerNotes>
      <GuildXPContribution>0</GuildXPContribution>
    </Member>
    <Member>
      <Name>Aetheldine</Name>
      <Rank>7</Rank>
      <Level>47</Level>
      <Calling>Mage</Calling>
      <Joined>2011-03-22T07:55:33.649</Joined>
      <IsOnline>False</IsOnline>
      <AFK>False</AFK>
      <LastLogOutTime>2011-04-30T10:12:34.251</LastLogOutTime>
      <PersonalNotes></PersonalNotes>
      <OfficerNotes>Main - Aetheldine, Daughter of Zeherah</OfficerNotes>
      <GuildXPContribution>0</GuildXPContribution>
    </Member>
    <Member>
      <Name>Rochas</Name>
      <Rank>7</Rank>
      <Level>3</Level>
      <Calling>Rogue</Calling>
      <Joined>2011-03-23T11:37:32.905</Joined>
      <IsOnline>False</IsOnline>
      <AFK>False</AFK>
      <LastLogOutTime>2011-03-28T08:31:44.472</LastLogOutTime>
      <PersonalNotes></PersonalNotes>
      <OfficerNotes>Main - Rochas</OfficerNotes>
      <GuildXPContribution>0</GuildXPContribution>
    </Member>
    <Member>
      <Name>Saries</Name>
      <Rank>9</Rank>
      <Level>21</Level>
      <Calling>Rogue</Calling>
      <Joined>2011-03-24T14:47:37.552</Joined>
      <IsOnline>False</IsOnline>
      <AFK>False</AFK>
      <LastLogOutTime>2011-04-21T03:56:46.176</LastLogOutTime>
      <PersonalNotes></PersonalNotes>
      <OfficerNotes>Alt - Sari</OfficerNotes>
      <GuildXPContribution>0</GuildXPContribution>
    </Member>
    <Member>
      <Name>Burls</Name>
      <Rank>8</Rank>
      <Level>18</Level>
      <Calling>Cleric</Calling>
      <Joined>2011-04-14T08:38:31.410</Joined>
      <IsOnline>False</IsOnline>
      <AFK>False</AFK>
      <LastLogOutTime>2011-04-30T07:05:24.929</LastLogOutTime>
      <PersonalNotes></PersonalNotes>
      <OfficerNotes>Alt - Burley</OfficerNotes>
      <GuildXPContribution>0</GuildXPContribution>
    </Member>
    <Member>
      <Name>Sar</Name>
      <Rank>6</Rank>
      <Level>23</Level>
      <Calling>Cleric</Calling>
      <Joined>2011-03-26T09:39:21.666</Joined>
      <IsOnline>False</IsOnline>
      <AFK>False</AFK>
      <LastLogOutTime>2011-04-28T08:24:23.119</LastLogOutTime>
      <PersonalNotes>mew mew I&apos;m a kitty</PersonalNotes>
      <OfficerNotes>Alt - Kitsa</OfficerNotes>
      <GuildXPContribution>0</GuildXPContribution>
    </Member>
    <Member>
      <Name>Melusine</Name>
      <Rank>6</Rank>
      <Level>19</Level>
      <Calling>Mage</Calling>
      <Joined>2011-03-27T00:46:51.63</Joined>
      <IsOnline>False</IsOnline>
      <AFK>False</AFK>
      <LastLogOutTime>2011-04-30T00:10:55.230</LastLogOutTime>
      <PersonalNotes>Monz</PersonalNotes>
      <OfficerNotes>Alt - Monz</OfficerNotes>
      <GuildXPContribution>0</GuildXPContribution>
    </Member>
    <Member>
      <Name>Jipheal</Name>
      <Rank>9</Rank>
      <Level>20</Level>
      <Calling>Mage</Calling>
      <Joined>2011-04-02T08:38:48.362</Joined>
      <IsOnline>False</IsOnline>
      <AFK>False</AFK>
      <LastLogOutTime>2011-04-19T02:55:30.224</LastLogOutTime>
      <PersonalNotes></PersonalNotes>
      <OfficerNotes>Main - Old Tarzzan</OfficerNotes>
      <GuildXPContribution>0</GuildXPContribution>
    </Member>
    <Member>
      <Name>Jhentar</Name>
      <Rank>5</Rank>
      <Level>21</Level>
      <Calling>Warrior</Calling>
      <Joined>2011-03-31T14:02:30.11</Joined>
      <IsOnline>False</IsOnline>
      <AFK>False</AFK>
      <LastLogOutTime>2011-04-09T15:32:51.930</LastLogOutTime>
      <PersonalNotes></PersonalNotes>
      <OfficerNotes>Main - Jhentar</OfficerNotes>
      <GuildXPContribution>0</GuildXPContribution>
    </Member>
    <Member>
      <Name>Jippo</Name>
      <Rank>7</Rank>
      <Level>41</Level>
      <Calling>Cleric</Calling>
      <Joined>2011-04-06T00:31:10.735</Joined>
      <IsOnline>False</IsOnline>
      <AFK>False</AFK>
      <LastLogOutTime>2011-04-29T13:09:32.146</LastLogOutTime>
      <PersonalNotes></PersonalNotes>
      <OfficerNotes>Main - Jip</OfficerNotes>
      <GuildXPContribution>0</GuildXPContribution>
    </Member>
    <Member>
      <Name>Suzume</Name>
      <Rank>5</Rank>
      <Level>46</Level>
      <Calling>Mage</Calling>
      <Joined>2011-04-30T07:12:41.953</Joined>
      <IsOnline>False</IsOnline>
      <AFK>False</AFK>
      <LastLogOutTime>2011-04-30T10:11:10.742</LastLogOutTime>
      <PersonalNotes></PersonalNotes>
      <OfficerNotes>Main - Ash</OfficerNotes>
      <GuildXPContribution>0</GuildXPContribution>
    </Member>
    <Member>
      <Name>Atane</Name>
      <Rank>5</Rank>
      <Level>49</Level>
      <Calling>Warrior</Calling>
      <Joined>2011-04-23T12:20:24.66</Joined>
      <IsOnline>False</IsOnline>
      <AFK>False</AFK>
      <LastLogOutTime>2011-04-29T13:30:10.241</LastLogOutTime>
      <PersonalNotes></PersonalNotes>
      <OfficerNotes>Main - Atane (AN WoW)</OfficerNotes>
      <GuildXPContribution>0</GuildXPContribution>
    </Member>
    <Member>
      <Name>Fourteen</Name>
      <Rank>6</Rank>
      <Level>26</Level>
      <Calling>Mage</Calling>
      <Joined>2011-04-17T06:23:50.444</Joined>
      <IsOnline>False</IsOnline>
      <AFK>False</AFK>
      <LastLogOutTime>2011-04-30T04:16:37.186</LastLogOutTime>
      <PersonalNotes>I&apos;m a number! (Kal)</PersonalNotes>
      <OfficerNotes>Alt - Kal</OfficerNotes>
      <GuildXPContribution>0</GuildXPContribution>
    </Member>
    <Member>
      <Name>Khelud</Name>
      <Rank>6</Rank>
      <Level>24</Level>
      <Calling>Rogue</Calling>
      <Joined>2011-04-17T00:41:38.923</Joined>
      <IsOnline>False</IsOnline>
      <AFK>False</AFK>
      <LastLogOutTime>2011-04-30T09:31:02.11</LastLogOutTime>
      <PersonalNotes></PersonalNotes>
      <OfficerNotes>Alt - Khelud</OfficerNotes>
      <GuildXPContribution>0</GuildXPContribution>
    </Member>
    <Member>
      <Name>Khel</Name>
      <Rank>5</Rank>
      <Level>46</Level>
      <Calling>Cleric</Calling>
      <Joined>2011-04-17T08:47:35.888</Joined>
      <IsOnline>False</IsOnline>
      <AFK>False</AFK>
      <LastLogOutTime>2011-04-30T09:19:51.652</LastLogOutTime>
      <PersonalNotes></PersonalNotes>
      <OfficerNotes>Main - Khelud</OfficerNotes>
      <GuildXPContribution>0</GuildXPContribution>
    </Member>
    <Member>
      <Name>Jark</Name>
      <Rank>4</Rank>
      <Level>20</Level>
      <Calling>Mage</Calling>
      <Joined>2011-04-16T01:29:27.34</Joined>
      <IsOnline>False</IsOnline>
      <AFK>False</AFK>
      <LastLogOutTime>2011-04-27T05:56:38.962</LastLogOutTime>
      <PersonalNotes></PersonalNotes>
      <OfficerNotes>Alt - Jack</OfficerNotes>
      <GuildXPContribution>0</GuildXPContribution>
    </Member>
    <Member>
      <Name>Wayah</Name>
      <Rank>9</Rank>
      <Level>9</Level>
      <Calling>Cleric</Calling>
      <Joined>2011-04-24T07:18:25.503</Joined>
      <IsOnline>False</IsOnline>
      <AFK>False</AFK>
      <LastLogOutTime>2011-04-28T21:10:06.375</LastLogOutTime>
      <PersonalNotes>Avia</PersonalNotes>
      <OfficerNotes>Main - Avia</OfficerNotes>
      <GuildXPContribution>0</GuildXPContribution>
    </Member>
    <Member>
      <Name>Silje</Name>
      <Rank>6</Rank>
      <Level>1</Level>
      <Calling>Mage</Calling>
      <Joined>2011-04-19T07:33:41.171</Joined>
      <IsOnline>False</IsOnline>
      <AFK>False</AFK>
      <LastLogOutTime>2011-04-19T07:34:24.307</LastLogOutTime>
      <PersonalNotes></PersonalNotes>
      <OfficerNotes>Alt - Kitsa</OfficerNotes>
      <GuildXPContribution>0</GuildXPContribution>
    </Member>
    <Member>
      <Name>Iridal</Name>
      <Rank>4</Rank>
      <Level>28</Level>
      <Calling>Cleric</Calling>
      <Joined>2011-04-19T13:30:14.474</Joined>
      <IsOnline>False</IsOnline>
      <AFK>False</AFK>
      <LastLogOutTime>2011-04-27T09:54:14.951</LastLogOutTime>
      <PersonalNotes>Dev with BEWBS</PersonalNotes>
      <OfficerNotes>Alt - Devoran</OfficerNotes>
      <GuildXPContribution>0</GuildXPContribution>
    </Member>
    <Member>
      <Name>Astill</Name>
      <Rank>5</Rank>
      <Level>4</Level>
      <Calling>Rogue</Calling>
      <Joined>2011-04-20T13:31:52.231</Joined>
      <IsOnline>False</IsOnline>
      <AFK>False</AFK>
      <LastLogOutTime>2011-04-22T08:29:59.948</LastLogOutTime>
      <PersonalNotes></PersonalNotes>
      <OfficerNotes>Main - Astill</OfficerNotes>
      <GuildXPContribution>0</GuildXPContribution>
    </Member>
    <Member>
      <Name>Zhorrn</Name>
      <Rank>5</Rank>
      <Level>21</Level>
      <Calling>Cleric</Calling>
      <Joined>2011-04-25T04:28:56.963</Joined>
      <IsOnline>True</IsOnline>
      <AFK>False</AFK>
      <LastLogOutTime>2011-04-30T04:23:33.689</LastLogOutTime>
      <PersonalNotes></PersonalNotes>
      <OfficerNotes>Main - Zhrorn (EQ1 Shaman)</OfficerNotes>
      <GuildXPContribution>0</GuildXPContribution>
    </Member>
  </Members>
</Guild>
